[{"fish":"Скат полярный","weight":"9.281 кг","location":"Норвежское море","gamer":"Dobrik10","bait":"Мёртвая макрель","date":"18.04.24"},{"fish":"Скат полярный","weight":"8.227 кг","location":"Норвежское море","gamer":"sergjr33","bait":"Lynns Huge Minnow 120-007","date":"16.04.24"},{"fish":"Скат полярный","weight":"7.837 кг","location":"Норвежское море","gamer":"KJIyMbA","bait":"Hunter 300-5","date":"15.04.24"},{"fish":"Скат полярный","weight":"7.812 кг","location":"Норвежское море","gamer":"Ded Ded","bait":"Natural Squid - 23 - 02","date":"17.04.24"},{"fish":"Скат полярный","weight":"7.555 кг","location":"Норвежское море","gamer":"ВсемПоЛещу","bait":"Pilker №2-800 RD","date":"17.04.24"}]