{"location":"","locationId":"","title":"","bio":"#ахтуба \nр. Ахтуба \n🇷🇺Россия\nАМУР БЕЛЫЙ\nТочка клева: 117:101\nКлипса: 8 метров\n\nВся информация по РР4 на нашем сайте - rr4farmtrof.com/","pva":"","dip":"","clips":"","bite":"","elements":"","inserts":"","like":"7","fish":"","fishId":"","dateTime":0,"date":"","hash":"","id":0,"reposts":"","points":null,"pointKey":"","groupId":"","images":["https://sun6-20.userapi.com/s/v1/ig2/jN66PyP6qwl4VFZT7UwGaNkd4d-uKeQmJlGV8TGUUgRBIid_pMDHF2jr3KZVHSk6-FDdL6PDKFk9XrvAxODdpdGP.jpg?quality=95\u0026as=32x18,48x27,72x41,108x61,160x90,240x135,360x203,480x270,540x304,640x360,720x405,1080x608,1280x720,1440x810,1880x1058\u0026from=bu\u0026cs=1880x0","https://sun6-20.userapi.com/s/v1/ig2/OQFAJSVBaaRZNiin8AmHM18-6w15g8upTjSMPE43Jhk7WlAJEzMqPgKIPTw87Cs-h_06TNGN5r6sEBKcGWJPL0GZ.jpg?quality=95\u0026as=32x18,48x27,72x41,108x61,160x90,240x135,360x203,480x270,540x304,640x360,720x405,1080x608,1280x720,1440x810,1880x1058\u0026from=bu\u0026cs=1880x0","https://sun6-20.userapi.com/s/v1/ig2/ZM9uzyZXa714OKrCvLRebhbaS0xAatliBvK35ugJrVTSrkSEUxxk7zM8s4p7AD_fbwwOzZHeoI4Dcs6nLWDarDmB.jpg?quality=95\u0026as=32x18,48x27,72x41,108x61,160x90,240x135,360x203,480x270,540x304,640x360,720x405,1080x608,1280x720,1440x810,1880x1058\u0026from=bu\u0026cs=1880x0","https://sun6-21.userapi.com/s/v1/ig2/cqg1PrechlRqfH1N5SVBd9_ZyepOF0_qKFtMs5nPJ8MKrmvyVyJDM7Vouu5Tjiv-qjsCibJaVafy23mpFeQYZgTg.jpg?quality=95\u0026as=32x18,48x27,72x41,108x61,160x90,240x135,360x203,480x270,540x304,640x360,720x405,1080x608,1280x720,1440x810,1880x1058\u0026from=bu\u0026cs=1880x0","https://sun6-21.userapi.com/s/v1/ig2/Z6YsHqSCxd6zoV80DKazyboBlFNOdSm0IbBG4mKJERoiIrsIMZWtsSuGApnEVILkTKFFWxu50_AhVxAVGQpf9dFX.jpg?quality=95\u0026as=32x18,48x27,72x41,108x61,160x90,240x135,360x203,480x270,540x304,640x360,720x405,1080x608,1280x720,1440x810,1880x1058\u0026from=bu\u0026cs=1880x0"]}