{"location":"","locationId":"","title":"","bio":"#ахтуба \nр. Ахтуба \n🇷🇺Россия\nКОЛЮШКА МАЛАЯ ЮЖНАЯ трофей\nТочка клева: 107:80 клипса 6 метров\nКлев очень активный плотвы, ночью колюшка не клюет. Ходил пару дней на нее. Всем нхнч","pva":"","dip":"","clips":"","bite":"","elements":"","inserts":"","like":"2","fish":"","fishId":"","dateTime":0,"date":"","hash":"","id":0,"reposts":"","points":null,"pointKey":"","groupId":"","images":["https://sun6-22.userapi.com/s/v1/ig2/Fbpfprwlmrzrm6yh5G8UUdQxYwI7ejrqvKZDxZgtoi8BoGqpbNCDYWcuh_6N7DNbbvB0B7G9caGaQLytmQe8j7jm.jpg?quality=95\u0026as=32x18,48x27,72x40,108x61,160x90,240x135,360x202,480x270,540x304,640x360,720x405,1080x607,1280x720,1440x810,1920x1080\u0026from=bu\u0026cs=1920x1080","https://sun6-21.userapi.com/s/v1/ig2/oKSlCTHhdNGtZXkE2XYPzz1byhtFo-DeeuBcpEi6ok7l7BAiIjZ0foaj5NmMpARV3VywJvzjDyRm8VZFPVxnycVc.jpg?quality=95\u0026as=32x18,48x27,72x40,108x61,160x90,240x135,360x202,480x270,540x304,640x360,720x405,1080x607,1280x720,1440x810,1920x1080\u0026from=bu\u0026cs=1920x1080","https://sun6-21.userapi.com/s/v1/ig2/5tiHPMUSQ6W590wsuc_BRY0LLln5o-0rJXOpLgNB3IGqs4MFFImroWZAEKQVQhWmjRmyynINW8bphtrliymFhRVx.jpg?quality=95\u0026as=32x18,48x27,72x40,108x61,160x90,240x135,360x202,480x270,540x304,640x360,720x405,1080x607,1280x720,1440x810,1920x1080\u0026from=bu\u0026cs=1920x1080","https://sun6-21.userapi.com/s/v1/ig2/cNC4Ooeg-Rn6Zyb45W3S-L9Biz73dOkhYGnCoUGbj_XdxhRUeaoOVcCjUdWzUKKpHMKHDOMT69CVOVROxET4fqOH.jpg?quality=95\u0026as=32x18,48x27,72x40,108x61,160x90,240x135,360x202,480x270,540x304,640x360,720x405,1080x607,1280x720,1440x810,1920x1080\u0026from=bu\u0026cs=1920x1080","https://sun6-23.userapi.com/s/v1/ig2/CuGAZ4HszDUd3l5Zvsv715-xKhCVYdEVZSCKMM9YoO8xXaz2Ar0YS1eSy95QOHzE8JAY8owo-BsoiOLwdKUPXNr-.jpg?quality=95\u0026as=32x18,48x27,72x40,108x61,160x90,240x135,360x202,480x270,540x304,640x360,720x405,1080x607,1280x720,1440x810,1920x1080\u0026from=bu\u0026cs=1920x1080"]}