{"location":"","locationId":"","title":"","bio":"#ахтуба\nр.Ахтуба\n🇷🇺 Россия \nОСЁТР РУССКИЙ троф \nТочка ловли: 33:103 клипса 15 метров \nОстальное всё на скриншотах","pva":"","dip":"","clips":"","bite":"","elements":"","inserts":"","like":"10","fish":"","fishId":"","dateTime":0,"date":"","hash":"","id":0,"reposts":"","points":null,"pointKey":"","groupId":"","images":["https://sun6-20.userapi.com/s/v1/ig2/VrCypIBvM1QqlXdmShFroz4F5M7CzzsuFgfJtjypyDArQPmRNwkDlFFArbVDUSr2hek_14zCwu1KukIH99QjAbJV.jpg?quality=95\u0026as=32x18,48x27,72x40,108x61,160x90,240x135,360x202,480x270,540x304,640x360,720x405,1080x607,1280x720,1440x810,1920x1080\u0026from=bu\u0026cs=1920x1080","https://sun6-23.userapi.com/s/v1/ig2/9Fjt51Iagmhci5wyWgFqT8z-Yon1xSmJwnYfGFHi6MBfDBGKvn4vD9ThZdamP6R2Nimyo9zaN2mVdhw-FoNEoBtO.jpg?quality=95\u0026as=32x18,48x27,72x40,108x61,160x90,240x135,360x202,480x270,540x304,640x360,720x405,1080x607,1280x720,1440x810,1920x1080\u0026from=bu\u0026cs=1920x1080","https://sun6-20.userapi.com/s/v1/ig2/Oyc4WH5Z4Hh414zKCeLS-InH5YwGAwJscM3uBBATcTe0OctcRKoWYjirUwm0ksE1xZbqs3EJTuDDoRGuiOI5Y-vm.jpg?quality=95\u0026as=32x18,48x27,72x40,108x61,160x90,240x135,360x202,480x270,540x304,640x360,720x405,1080x607,1280x720,1440x810,1920x1080\u0026from=bu\u0026cs=1920x1080","https://sun6-20.userapi.com/s/v1/ig2/aEz2ABCPe8et9zfrwHUxynfxTSlh2F8TTcMe-H_YL0P6CkmoR5q0RqFKgLiGr-q3sexACvxTR1fdKo97alPaYj8P.jpg?quality=95\u0026as=32x18,48x27,72x40,108x61,160x90,240x135,360x202,480x270,540x304,640x360,720x405,1080x607,1280x720,1440x810,1920x1080\u0026from=bu\u0026cs=1920x1080","https://sun6-21.userapi.com/s/v1/ig2/6xENFjFRTUum3qzdN4kqTXx5pt7IE-KmZqxv7Nc05onfpEHzIN3wuJY7Pz5GgxVxFvSbP77bJDjsE2a1U8rIUcbp.jpg?quality=95\u0026as=32x18,48x27,72x40,108x61,160x90,240x135,360x202,480x270,540x304,640x360,720x405,1080x607,1280x720,1440x810,1920x1080\u0026from=bu\u0026cs=1920x1080"]}