{"location":"","locationId":"","title":"","bio":"#медвежье \nоз. Медвежье \n🇨🇳 China \nКАРП ЗЕРКАЛЬНЫЙ троф\nКАРП ЧЕШУЙЧАТЫЙ троф\nТочка клева: 55:31, клипса: 17 метров\nНаживка: Свежая малина 20 + Малиновый джем 20\nДип: Малиновый крем\nПВА: молотая кукуруза + малиновый джем 8, 12, 16 + Свежая малина Pop Ups 16 (дробл) + малина","pva":"","dip":"","clips":"","bite":"","elements":"","inserts":"","like":"0","fish":"","fishId":"","dateTime":0,"date":"","hash":"","id":0,"reposts":"","points":null,"pointKey":"","groupId":"","images":["https://sun6-21.userapi.com/s/v1/ig2/4c1J9Xh9NOW8C44LTP2utG6pfrpt4vhP-CoLGOdPB8rsxI6p5YrtbDgJPSOKxqOB1QBjmpOhvBaID5ePix9kkXoH.jpg?quality=95\u0026as=32x18,48x27,72x41,108x61,160x90,240x135,360x203,480x270,540x304,640x360,720x405,1000x563\u0026from=bu\u0026cs=1000x563","https://sun6-22.userapi.com/s/v1/ig2/_TTTmorY2s1ucYq6zpkOtvNaI4d33JWh1IwKfqi-l8_byH0ylvINdnxdELgT_-4Vxtjqrr4cC0cmYvE5kZhKmDQL.jpg?quality=95\u0026as=32x16,48x24,72x35,108x53,160x79,240x118,360x177,480x236,540x266,640x315,720x355,960x473\u0026from=bu\u0026cs=960x473","https://sun6-22.userapi.com/s/v1/ig2/Z2J6Z4Vylx6qvqumUviz4qBMzFWnBaTVE9JmOeV0CIRABAdK470S4JV-0vm6VfELu7rycCqC7v93iKccgAXQzFOu.jpg?quality=95\u0026as=32x17,48x26,72x39,108x58,160x86,240x129,360x193,480x258,540x290,640x344,720x387,907x487\u0026from=bu\u0026cs=907x487","https://sun9-68.userapi.com/s/v1/ig2/5E7GOKd1AoD_CaNfpjX7NO9imf3MaobI91KIVZ2VmEiv0kSRWQowlyq_HfwtrHKsYSi917Fd8ysKz69LzgFgjh8V.jpg?quality=95\u0026as=32x38,48x58,72x86,108x130,160x192,240x288,360x432,480x576,540x648,640x768,720x864,800x960\u0026from=bu\u0026cs=800x960","https://sun6-22.userapi.com/s/v1/ig2/6jaSD0vSFbXpe3BovttYrbZbwibFcrkqv6LSz20juh6JuNJX0wmVFAtGzgjykFC7zUwmgiI-J2ZTDqreICJz6oSf.jpg?quality=95\u0026as=32x32,48x48,72x72,108x108,160x159,240x239,360x359,480x479,540x538,640x638,651x649\u0026from=bu\u0026cs=651x649","https://sun6-22.userapi.com/s/v1/ig2/Oiy59Aw8d-I1tpizpC4988AtBILNk52womD0miQfM8PK1lQvW7-S0d1Kgk_dhHsGyvOyK05acJ-m1cCrZJr7TXh9.jpg?quality=95\u0026as=32x16,48x24,72x37,108x55,160x81,240x122,360x183,480x244,540x274,640x325,720x366,1000x508\u0026from=bu\u0026cs=1000x508"]}