{"location":"","locationId":"","title":"","bio":"#вьюнок \nр. Вьюнок \n🇨🇳 China \nБЕЛОГЛАЗКА троф\nТочка клева: 118:124, глубина 175 см\nНаживка: червь + червь навозный","pva":"","dip":"","clips":"","bite":"","elements":"","inserts":"","like":"6","fish":"","fishId":"","dateTime":0,"date":"","hash":"","id":0,"reposts":"","points":null,"pointKey":"","groupId":"","images":["https://sun6-21.userapi.com/s/v1/ig2/3sRKHV0yENxcSrHdf_x7skB9crjHaDNb-I92rov6JtUxfQ-z1krTYx1omFaeNNceQO7tuKT9sQarWtQqj8-CZEu9.jpg?quality=95\u0026as=32x18,48x27,72x41,108x61,160x90,240x135,360x203,480x270,540x304,640x360,720x405,1000x563\u0026from=bu\u0026cs=1000x563","https://sun6-23.userapi.com/s/v1/ig2/w8Y3fotQdsleAAAHX521wZxrKgqPBhT9ozBSTiDMRy6AqqNi6sgx577VgzU8MjEcOPs6XzELqGPKVhxNeKDUN7-D.jpg?quality=95\u0026as=32x18,48x27,72x41,108x61,160x90,240x135,360x203,480x270,540x304,640x360,720x405,1000x563\u0026from=bu\u0026cs=1000x563","https://sun9-57.userapi.com/s/v1/ig2/0qM2azJ7-ipDo_FoqkMZGcVT05FK4Kqq0t8ZGhQWS_uE3AeDvUhvWj_vDRWW63Xc8wLAQkjlMMLzGEk-qc9zfPzx.jpg?quality=95\u0026as=32x18,48x27,72x41,108x61,160x90,240x135,360x203,480x270,540x304,640x360,720x405,1000x563\u0026from=bu\u0026cs=1000x563","https://sun6-23.userapi.com/s/v1/ig2/2d-QN8OiuwWY7vqYRPkjuX6g_rOWCQj7MbuHA9eWzz3XM56xBtH-Da7f6hKqBQNJTBZ6yYNixP_ZEo2_wh8-zXq3.jpg?quality=95\u0026as=32x18,48x27,72x41,108x61,160x90,240x135,360x203,480x270,540x304,640x360,720x405,1000x563\u0026from=bu\u0026cs=1000x563","https://sun6-23.userapi.com/s/v1/ig2/VnABW-VTcPSLC7nUp-bau-M1q8CaDrVWYNuQaZwbSzlZ3QqdwyERIJ8tbisWCXednxZlSSTG5gNkYKovvmO-1W79.jpg?quality=95\u0026as=32x32,48x48,72x71,108x107,160x159,240x238,360x357,480x477,540x536,640x635,720x715,981x974\u0026from=bu\u0026cs=981x974"]}