{"location":"","locationId":"","title":"","bio":"#медное\nоз. Медное\n🇷🇺Россия\n\nЛИНЬ КВОЛЬСДОРФСКИЙ троф\nТочка клева: 67:59, клипса 5 метров \nНаживка: 2 иск. кукурузы Кокосовый крем \nДип: Кокосовый нектар \nПВА: молотая кукуруза + кокос и сливки 5, 7, 12 + кокос и сливки 12 поп ап дробленые + кокосовый крем \nТемпература: нормальная\nждал 40 минут)\n\nпоиск точек клева в VK - https://vk.com/wall-222013971_79277 \nпоиск точек клева в ТГ - https://t.me/pp4farmtrof/50537 \nпредложить пост в VK - https://vk.com/pp4farmtrof \nпредложить пост в ТГ - https://t.me/pp4farmtrof/102648\nгруппа VK (точки клева) - https://vk.com/pp4farmtrof \nсмотреть точки клева в телеграм - https://t.me/pp4farmtrof \nнаш чат телеграм - https://t.me/+uQHedikeO9Y3NmQy \nбарахолка вк - https://vk.com/baraholkamalcevidze \nбарахолка телеграм - https://t.me/pp4farmtrofMARKET \nстримы и видео рр4 - https://www.youtube.com/@rr4.farm.trof.malcevidze \nдискорд-общение - https://discord.gg/AdJGuGFD7Z","pva":"","dip":"","clips":"","bite":"","elements":"","inserts":"","like":"9","fish":"","fishId":"","dateTime":0,"date":"","hash":"","id":0,"reposts":"","points":null,"pointKey":"","groupId":"","images":["https://sun9-33.userapi.com/s/v1/if2/m8ep2RirJ1f81xhVPFFH6LfRfffO77dL18sSmy2U7t_St7hJB4GHgz9NE2nlqOOK-omEf_Hyy7YQmUWq4EHJvNn6.jpg?quality=96\u0026as=32x18,48x27,72x40,108x61,160x90,240x135,360x202,480x270,540x304,640x360,720x405,1080x607,1280x720,1440x810,1920x1080\u0026from=bu\u0026cs=1920x0","https://sun9-49.userapi.com/s/v1/if2/EHMx3T-cYr28tXrabPsR3Y88tYo4KXiONfibFfL6y9LKnGG7KMOexCR15giI-OTehpdFNU76OmyBS2I6ZzhpS1d3.jpg?quality=96\u0026as=32x18,48x27,72x40,108x61,160x90,240x135,360x202,480x270,540x304,640x360,720x405,1080x607,1280x720,1440x810,1920x1080\u0026from=bu\u0026cs=1920x0","https://sun9-70.userapi.com/s/v1/if2/x6d-uogDU_uU5X7GjOAjXVePe21EgsE2ssiCcp7CGD-v4S4VDdKetVARCPtH875Co_QstxOrrf-gw5e03HskztLj.jpg?quality=96\u0026as=32x18,48x27,72x40,108x61,160x90,240x135,360x202,480x270,540x304,640x360,720x405,1080x607,1280x720,1440x810,1920x1080\u0026from=bu\u0026cs=1920x0","https://sun6-23.userapi.com/s/v1/if2/NiCsuKSYZ53jmjq2pOT7-_IRAZqx0SpgJSe2D-3J999xYxHehQg0w-O9_rqL9fETkxUSsB-Sx2hiDpK3IucWimA0.jpg?quality=96\u0026as=32x18,48x27,72x40,108x61,160x90,240x135,360x202,480x270,540x304,640x360,720x405,1080x607,1280x720,1440x810,1920x1080\u0026from=bu\u0026cs=1920x0","https://sun9-13.userapi.com/s/v1/if2/BOfUxUUGWBUAVIiXN5otixe9SGwdad_2Ot-JVGsoq_BSXkPB90oinGUyqJJEBjJyR4cXm2rwcYYn94bGepYIeDm0.jpg?quality=96\u0026as=32x18,48x27,72x40,108x61,160x90,240x135,360x202,480x270,540x304,640x360,720x405,1080x607,1280x720,1440x810,1920x1080\u0026from=bu\u0026cs=1920x0","https://sun9-19.userapi.com/s/v1/if2/qY4nZy9Lajqml8Kd_8pqk2BK_SRp6nBbx0Bx75Obc6fyewe_06VqMx0gR_MjvJzHgfRsEEFHbU4bigVBLy2jf1HT.jpg?quality=96\u0026as=32x18,48x27,72x40,108x61,160x90,240x135,360x202,480x270,540x304,640x360,720x405,1080x607,1280x720,1440x810,1920x1080\u0026from=bu\u0026cs=1920x0"]}