{"location":"","locationId":"","title":"","bio":"#медное \nоз. Медное \n🇨🇳 China \nКАРАСЕКАРП троф\nЛИНЬ троф х 2\nТочка клева: 67:59, клипса 5 метров \nНаживка: Ваниль Pop-Up 14 + иск. кукуруза Сливки\nДип: Сливки\nПВА: молотый горох + Ваниль 14 (дробл) + ваниль 3 + сливки 4, 8 + ваниль\nТемпература нормальная\n\nпоиск точек клева в VK - https://vk.com/wall-222013971_79277\nпоиск точек клева в ТГ - https://t.me/pp4farmtrof/50537\nпредложить пост - https://vk.com/pp4farmtrof\nгруппа VK (точки клева) - https://vk.com/pp4farmtrof\nсмотреть точки клева в телеграм - https://t.me/pp4farmtrof\nнаш чат телеграм - https://t.me/+uQHedikeO9Y3NmQy\nбарахолка вк - https://vk.com/baraholkamalcevidze\nбарахолка телеграм - https://t.me/pp4farmtrofMARKET\nстримы и видео рр4 - https://www.youtube.com/@rr4.farm.trof.malcevidze\nдискорд-общение - https://discord.gg/AdJGuGFD7Z","pva":"","dip":"","clips":"","bite":"","elements":"","inserts":"","like":"2","fish":"","fishId":"","dateTime":0,"date":"","hash":"","id":0,"reposts":"","points":null,"pointKey":"","groupId":"","images":["https://sun9-1.userapi.com/s/v1/if2/C-KePin7GWTZ2yVePagRWHfh5E8m27uOmEB9th3EfUhHk_m81ApbPB2RFZkajxT2HylXLC6KlyKlwidqjdRhglbs.jpg?quality=96\u0026as=32x15,48x22,72x33,108x49,160x73,240x109,360x163,480x218,540x245,640x291,720x327,1000x454\u0026from=bu\u0026cs=1000x0","https://sun9-19.userapi.com/s/v1/ig2/I_hTH-vbrycRyowGzmKUO3Y2NeuuUPZYPq-fAKeFkA9yP93YoV1hRCdHqUabxoVkgy3YT3sP2HCvtjp2kUMwNMJj.jpg?quality=96\u0026as=32x55,48x82,72x124,108x186,160x275,240x412,360x619,480x825,540x928,544x935\u0026from=bu\u0026cs=544x0","https://sun9-88.userapi.com/s/v1/ig2/9OdjKK8c76rVkNSuvEw0-R5sh2AZPzhAvW0LGqTvDy0meK7t4M0kH8jMJDokxpkLKqMR3lt-46enZsmNkIK7Ua-G.jpg?quality=96\u0026as=32x54,48x81,72x121,108x182,160x270,240x405,360x607,480x810,540x911,544x918\u0026from=bu\u0026cs=544x0","https://sun6-23.userapi.com/s/v1/ig2/4ShbQUdJbFfV0zuK6n2qe1wpisaf0qrxBve56Xbh16a5o0kv-97No-vusvEfnPNSAf8tR7sFsnTEhuTNjN3ki8eG.jpg?quality=96\u0026as=32x56,48x85,72x127,108x191,160x282,240x423,360x635,480x847,526x928\u0026from=bu\u0026cs=526x0"]}