{"location":"","locationId":"","title":"","bio":"#медное\nоз. Медное\n🇨🇳 Китай\nКАРП КОИ ОРЭНДЗИ ОГОН\nТочка клева: 37:32\nКлипса: 31 метров\nНаживка: Клубника Pop-Up 25 + 2 иск. кукурузы Клубника\nДип: Клубника\nПрикормка: молотая кукуруза + клубника 4 + клубника 8 + клубника 10 + Клубника Pop-Up 15 (дробл) + клубника и специи\n\nКомментарий игрока:\n\"Оранжевый золотой - один заброс, трофей. 56:50 сидел на Карпа Супер Фрикс, неудачно 5 пришли, 37:32 оранжевый золотой одним забросом трофей - можно сказать, компенсация. 56:50 еще случайно зацепил одного голого Карпа, Супер Фрикс**, заклинило намертво.\"\n\nВся информация по РР4 на нашем сайте - https://rr4farmtrof.com/","pva":"","dip":"","clips":"","bite":"","elements":"","inserts":"","like":"5","fish":"","fishId":"","dateTime":0,"date":"","hash":"","id":0,"reposts":"","points":null,"pointKey":"","groupId":"","images":["https://sun6-21.userapi.com/s/v1/ig2/UpHvXw5ogMDFua-SvhnAA6EcritEUCEExbaxnqVkycwE8WRAxAqONs-tj-l2ctTE_gfd6KloFSJAqfHO4UiZtMw3.jpg?quality=96\u0026as=32x16,48x24,72x37,108x55,160x82,240x122,360x184,480x245,540x275,640x326,720x367,1000x510\u0026from=bu\u0026cs=1000x0","https://sun6-23.userapi.com/s/v1/ig2/gx6j8Mz4naYRxQfhWlkY0iaa5Vt_I7G1j6ThtmVvPPxj9yrXNtrPK0G3umOaBdbBUFCnGetbSTVaPZbSe7Phdr4a.jpg?quality=96\u0026as=32x23,48x34,72x52,108x77,160x115,240x172,360x258,480x344,540x387,640x458,720x516,1000x716\u0026from=bu\u0026cs=1000x0","https://sun6-21.userapi.com/s/v1/ig2/YChVUqkCn5lwBd5kdIZZbNPuG2dMRyVekEUPWimnGR8DEoUhliAzhmwEI6tCoKLyoyYwk5V85mCL2Mj8w1PQiUOU.jpg?quality=96\u0026as=32x25,48x37,72x55,108x83,160x123,240x185,360x277,480x370,540x416,640x493,720x554,1000x770\u0026from=bu\u0026cs=1000x0","https://sun6-23.userapi.com/s/v1/ig2/uNWm9nBmDitU3cgVvmlfhiQbBYootb-OJWIY8wVrCulgJy3lHLZZ6-M0tfr9m6lS36I7Nw1wCD_u6pOnsHRwG4P4.jpg?quality=96\u0026as=32x18,48x26,72x39,108x59,160x88,240x132,360x197,480x263,540x296,640x351,720x395,1000x548\u0026from=bu\u0026cs=1000x0"]}