{"location":"","locationId":"","title":"","bio":"#медное \nоз. Медное \n🇷🇺Россия \nЛИНЬ троф Х 2\nФАРМ 1 час : 1000 монет\nТемпература нормальная\nТочка клева: 57:50 клипса 6 - 8 метров \nНаживка: Иск. кукурузы Сливки \nДИП: Сливки \nПВА: на скрине\n\npp4farmtrof \nVK - pp4farmtrof \nVK - PP4FARMTROF","pva":"","dip":"","clips":"","bite":"","elements":"","inserts":"","like":"4","fish":"","fishId":"","dateTime":0,"date":"","hash":"","id":0,"reposts":"","points":null,"pointKey":"","groupId":"","images":["https://sun9-18.userapi.com/s/v1/ig2/9t7InrjwWo5u2gzTSqBV_JeXhcSmLJ5iqU7lwTnj4rCGIwLlUdHUFdmMAyTII0t3IhXklW6bq_OzcPWUsnve_YaW.jpg?quality=95\u0026as=32x18,48x27,72x40,108x61,160x90,240x135,360x202,480x270,540x304,640x360,720x405,1080x607,1280x720,1440x810,2560x1440\u0026from=bu\u0026cs=2560x1440","https://sun9-2.userapi.com/s/v1/ig2/IAQMnRVJe5grMB9O3MtMUjucOz4BTwKWCYI18YmziGqTNoz2hTQiRFq21W6sT3EtpmIvuB3l-mAJj2tHCkWz7N2m.jpg?quality=95\u0026as=32x18,48x27,72x40,108x61,160x90,240x135,360x202,480x270,540x304,640x360,720x405,1080x607,1280x720,1440x810,2560x1440\u0026from=bu\u0026cs=2560x1440","https://sun9-63.userapi.com/s/v1/ig2/oBYFX2aqj4f-vEyiTL4mu8TdjYYpyxfelWKrd8LHl8b8TK9_wzQkyA_n-hfCDl3W7VG8BKna-yrHcbY7A4vxyH_0.jpg?quality=95\u0026as=32x18,48x27,72x40,108x61,160x90,240x135,360x202,480x270,540x304,640x360,720x405,1080x607,1280x720,1440x810,2560x1440\u0026from=bu\u0026cs=2560x1440","https://sun6-23.userapi.com/s/v1/ig2/uho7-2_FDV-PlPvYPHWE6rmYTo-q7-_ZTFl13-I_mrh0myt_uBBcemOP3PqVZRLFIlM2Dmr4Nb8e0xLPmSiYV6kf.jpg?quality=95\u0026as=32x18,48x27,72x40,108x61,160x90,240x135,360x202,480x270,540x304,640x360,720x405,1080x607,1280x720,1440x810,2560x1440\u0026from=bu\u0026cs=2560x1440","https://sun9-50.userapi.com/s/v1/ig2/LEimnlBgNRB2Y6dS1lkxXQ-xRrgEzGCa6mAj3RtFDJj6JYqu2j3Vd-dY2X6QSYPXWbzh7uqCwK0eHPS8h_0A8jxp.jpg?quality=95\u0026as=32x18,48x27,72x40,108x61,160x90,240x135,360x202,480x270,540x304,640x360,720x405,1080x607,1280x720,1440x810,2560x1440\u0026from=bu\u0026cs=2560x1440","https://sun9-49.userapi.com/s/v1/ig2/CPEgxBBrAq5kWSlhpxt3GGQvxE-ueiLgWxqW_AyoAF8mJpcc37N0m8joMQAwJt2TKHHIizeZgOZqHco9zbpjdCiE.jpg?quality=95\u0026as=32x18,48x27,72x40,108x61,160x90,240x135,360x202,480x270,540x304,640x360,720x405,1080x607,1280x720,1440x810,2560x1440\u0026from=bu\u0026cs=2560x1440","https://sun6-23.userapi.com/s/v1/ig2/5XX61k3KgrzrOiLqLnaTx_ov7I_mxECum0jpuucQppAcEE2m5JnFIbP2iH145UKEnGm6EOGQbNRkJrkJ_MxODzaE.jpg?quality=95\u0026as=32x18,48x27,72x40,108x61,160x90,240x135,360x202,480x270,540x304,640x360,720x405,1080x607,1280x720,1440x810,2560x1440\u0026from=bu\u0026cs=2560x1440","https://sun9-55.userapi.com/s/v1/ig2/wwOhFDIfKx2yVrNlu5jY-4-Lb46zU9FX9Qh-WkxAmzIyXeOrYinhDL7082j6OXHa2fNr3KAf8y1Dv5L1tAcZcYyP.jpg?quality=95\u0026as=32x18,48x27,72x40,108x61,160x90,240x135,360x202,480x270,540x304,640x360,720x405,1080x607,1280x720,1440x810,2560x1440\u0026from=bu\u0026cs=2560x1440","https://sun9-49.userapi.com/s/v1/ig2/E-adaBAmOX0tfoMRZhwd2Kpr6sVSthgmzGjzEq6b5GxJBMvFaomV01OPbHjGer3GACxCFqPlwzebzRb5tlN02xhR.jpg?quality=95\u0026as=32x18,48x27,72x40,108x61,160x90,240x135,360x202,480x270,540x304,640x360,720x405,1080x607,1280x720,1440x810,2560x1440\u0026from=bu\u0026cs=2560x1440"]}