{"location":"","locationId":"","title":"","bio":"#медное\nоз. Медное\n🇨🇳 China\nТемпература НОРМАЛЬНАЯ\nКАРПЫ КОИ\nТочка клева: 48:51, клипса 10  метров\nНаживка: Свежая малина 20 + Малиновый джем 20\nДип: Малиновый крем\nПВА: молотая кукуруза + Свежая малина 20 (дробл) + малиновый джем 8, 12, 16 + малина\n\nпоиск точек клева в VK - https://vk.com/wall-222013971_79277 \nпоиск точек клева в ТГ - https://t.me/pp4farmtrof/50537 \nпредложить пост - https://vk.com/pp4farmtrof \nгруппа VK (точки клева) - https://vk.com/pp4farmtrof \nсмотреть точки клева в телеграм - https://t.me/pp4farmtrof \nнаш чат телеграм - https://t.me/+uQHedikeO9Y3NmQy \nбарахолка вк - https://vk.com/baraholkamalcevidze \nбарахолка телеграм - https://t.me/pp4farmtrofMARKET \nстримы и видео рр4 - https://www.youtube.com/@rr4.farm.trof.malcevidze \nдискорд-общение - https://discord.gg/AdJGuGFD7Z","pva":"","dip":"","clips":"","bite":"","elements":"","inserts":"","like":"9","fish":"","fishId":"","dateTime":0,"date":"","hash":"","id":0,"reposts":"","points":null,"pointKey":"","groupId":"","images":["https://sun9-78.userapi.com/s/v1/if2/DtSDpDCEuWLC_9DiU4Hl6PlQEu9Eb_Blxa6nTxCfVeozczzpzUeIeblKjkVfkCUz5uuwa8dSnvmqA0skn1MpT73s.jpg?quality=96\u0026as=32x12,48x18,72x27,108x40,160x60,240x90,360x135,480x180,540x202,640x239,720x269,1080x404,1200x449\u0026from=bu\u0026cs=1200x449","https://sun9-27.userapi.com/s/v1/if2/tMSgYIejPzTkla5ShA3AzGA_d7RR2Wzd8LB9xN3WhlKPUYl5rZNGQ3PTFiJto7MYGLVNwj-YpkRmk1OuNjlHEfsG.jpg?quality=96\u0026as=32x16,48x24,72x36,108x54,160x81,240x121,360x181,480x242,540x272,640x323,720x363,1080x544,1200x605\u0026from=bu\u0026cs=1200x605","https://sun9-53.userapi.com/s/v1/if2/wtHEK9MQOqJidOWqCwznQTTwznI1x-qKDJz7v4LqyXYqeKI4rK6QIoXKxeMsC7Kpj569BRRfMRY2prozn5dohQN5.jpg?quality=96\u0026as=32x20,48x29,72x44,108x66,160x98,240x147,360x220,480x293,540x330,640x391,720x440,1080x660,1178x720\u0026from=bu\u0026cs=1178x720","https://sun9-59.userapi.com/s/v1/if2/SisLEnM0zY58uQg3AQeWtLwH-DA8_jX8Thy-vnD3SASziFrLs9KVq8HBLjX8jMvpCrchrojC_C9CFppBdXCqcGno.jpg?quality=96\u0026as=32x31,48x47,72x71,108x106,160x158,240x236,360x354,480x473,540x532,640x630,720x709,1080x1063,1170x1152\u0026from=bu\u0026cs=1170x1152"]}