{"location":"","locationId":"","title":"","bio":"#медное\nоз. Медное\n🇨🇳 Китай\nФАРМ\nТочка клева: 56:50\nКлипса: 6 метров\nНаживка: 2 иск. кукурузы Кокосовый крем\nДип: Кокосовый нектар\nПрикормка: молотая кукуруза + кокос и сливки 5 + кокос и сливки 7 + кокос и сливки 12 + бисквит + кокосовый крем\nТемпература воды: нормальная\n\nКомментарий игрока:\n\"Кокос неплохой клев, сливки. Было несколько поклевок редкой рыбы, могут быть мощные поклевки линя Динкенбюльского, будьте внимательны.\"\n\nВся информация по РР4 на нашем сайте - https://rr4farmtrof.com/","pva":"","dip":"","clips":"","bite":"","elements":"","inserts":"","like":"2","fish":"","fishId":"","dateTime":0,"date":"","hash":"","id":0,"reposts":"","points":null,"pointKey":"","groupId":"","images":["https://sun9-21.userapi.com/s/v1/ig2/nT7E76m7Ki_yPSnKnX4f9u2zf_K7QwrNIbxXhocyxxtbPpxzSfyzFh9dVXm347tTL9w6_vcNHmBc-ZOZwFoTIphr.jpg?quality=96\u0026as=32x18,48x26,72x40,108x59,160x88,240x132,360x198,480x264,540x297,640x351,720x395,1080x593,1200x659\u0026from=bu\u0026cs=1200x0","https://sun6-22.userapi.com/s/v1/ig2/I4U_8L0oPLZ26ANr6r3ZWWAbpGUlL8GMCRuiQJeRrUezfd_lz-LGeoxJv2jnaxBBFYu58gC_6LPmE2VemuW4-TPk.jpg?quality=96\u0026as=32x36,48x54,72x81,108x122,160x181,240x271,360x407,480x543,540x611,640x724,720x814,800x905\u0026from=bu\u0026cs=800x0","https://sun6-21.userapi.com/s/v1/ig2/e99u1EJTrR6LmrxVbaFEGzSCq9pUdoryFOW1velVrQcjC9kFYNRtKEZ4MzXHATTAhtcMmIT59hcvseQ8Z-S6v_GX.jpg?quality=96\u0026as=32x24,48x36,72x54,108x81,160x121,240x181,360x272,480x362,540x408,640x483,720x543,1060x800\u0026from=bu\u0026cs=1060x0","https://sun6-20.userapi.com/s/v1/ig2/zyiRvtM5evPBCm2vBtq-w91MN5J_SKWZ7Lx4erJYvm94G2YY64MdPQutNppi1AwK_WJjkdHWbEMuL_EoMXYru_w3.jpg?quality=96\u0026as=32x47,48x70,72x106,108x159,160x235,240x353,360x529,480x705,482x708\u0026from=bu\u0026cs=482x0"]}