{"location":"","locationId":"","title":"","bio":"#медное \nоз.Медное \n🇷🇺Россия \nКАРАСЕКАРП троф \nТочка клева: 67:59, клипса 9 метров \nНаживка: на скринах \nДип: Банановый удар \nТемпература повышенная","pva":"","dip":"","clips":"","bite":"","elements":"","inserts":"","like":"9","fish":"","fishId":"","dateTime":0,"date":"","hash":"","id":0,"reposts":"","points":null,"pointKey":"","groupId":"","images":["https://sun6-23.userapi.com/s/v1/ig2/95hXq45eRJtPhp1dq-3V3CTeBuoAV84Oe6yQvxi57Kw8LVW4O6MjgRxW9ra1kG1I3oLmurU55miezMyR9CbdHUaj.jpg?quality=96\u0026as=32x18,48x27,72x40,108x61,160x90,240x135,360x202,480x270,540x304,640x360,720x405,1080x607,1280x720,1440x810,1920x1080\u0026from=bu\u0026cs=1920x1080","https://sun6-21.userapi.com/s/v1/ig2/06pm_oYasLG4SRKRkhpsBUcJNGrKxB9HqDam_tGlPbsSGR2YqwZSea1oYdnZcQOu7ak9iW7D0ovBEuSQnS5N3b14.jpg?quality=96\u0026as=32x18,48x27,72x40,108x61,160x90,240x135,360x202,480x270,540x304,640x360,720x405,1080x607,1280x720,1440x810,1920x1080\u0026from=bu\u0026cs=1920x1080","https://sun6-21.userapi.com/s/v1/ig2/YdhAWkx-UoUGjPq_pZmKHjI5PlADq1Q-QZal4EbhirWI7bS4QfnhOEbhHpNkxxLZlH4XxmfEO20XieT59jyBZwuy.jpg?quality=96\u0026as=32x18,48x27,72x40,108x61,160x90,240x135,360x202,480x270,540x304,640x360,720x405,1080x607,1280x720,1440x810,1920x1080\u0026from=bu\u0026cs=1920x1080","https://sun6-22.userapi.com/s/v1/ig2/JQ_6fQwbcChpuzRFRbeN6dpikr9udc9mq52pVCbmtCnD8-azuRI75zHnsPFE0fOFCdZM_qmQ5Ahm_eB1uiLuhctO.jpg?quality=96\u0026as=32x18,48x27,72x40,108x61,160x90,240x135,360x202,480x270,540x304,640x360,720x405,1080x607,1280x720,1440x810,1920x1080\u0026from=bu\u0026cs=1920x1080","https://sun6-21.userapi.com/s/v1/ig2/Jng-bCEhCmvPsmyVeqBiSsTpYdaSosynm_ImHtC0ACCzLL4x1SlivTMb9zaaQdrXr7hTT-NMLDD-038gXfaYItJ-.jpg?quality=96\u0026as=32x18,48x27,72x40,108x61,160x90,240x135,360x202,480x270,540x304,640x360,720x405,1080x607,1280x720,1440x810,1920x1080\u0026from=bu\u0026cs=1920x1080"]}