{"location":"","locationId":"","title":"","bio":"#комариное\nКомариное\n🇨🇳 Китай\nЛЯГУШКА\nТочка клева: 53:75\nГлубина: 18 см\nСила заброса: 125%\nКрючок: Simmons Happy Hook CL-11 S20\nНаживка: муха\n\nКомментарий игрока:\n\"За десять минут на четвертом забросе поймал звезду. Открыл рыбака на первой карте. Это была самая быстрая охота на звезду. Еще иностранцы подходили спрашивать, но я ничего не понял.\"\n\nВся информация по РР4 на нашем сайте - https://rr4farmtrof.com/","pva":"","dip":"","clips":"","bite":"","elements":"","inserts":"","like":"0","fish":"","fishId":"","dateTime":0,"date":"","hash":"","id":0,"reposts":"","points":null,"pointKey":"","groupId":"","images":["https://sun9-72.userapi.com/s/v1/ig2/zOk1igdYZtZaaQneqqQGRtWMd52nOsHwFvTBkRhBxaPxySe7rcgjKjUTmWd3i25pTRtXkhWo4vdHom5xDU7hh7Tr.jpg?quality=96\u0026as=32x20,48x30,72x45,108x67,160x100,240x150,360x225,480x300,540x337,640x400,720x450,1080x675,1280x800,1440x900,2560x1600\u0026from=bu\u0026cs=2560x0","https://sun9-57.userapi.com/s/v1/ig2/U0naAiBanVXnIcRHe_3uDaybpGOmOb6FiOBkuXwtxwmDB7RONlh-5j-KjPdwO65pwTf64mK93PDbHqvzI3LQKIPT.jpg?quality=96\u0026as=32x20,48x30,72x45,108x67,160x100,240x150,360x225,480x300,540x337,640x400,720x450,1080x675,1280x800,1440x900,2560x1600\u0026from=bu\u0026cs=2560x0","https://sun9-53.userapi.com/s/v1/ig2/hdLkB7-ZWPdiEx6FCNX_ZYAFMQdbJujzRnv1B7l3yzfsh0Wc-HxColuW3HHUNU00jhu6fF29Ecg3Vl3omrCo3qaz.jpg?quality=96\u0026as=32x20,48x30,72x45,108x67,160x100,240x150,360x225,480x300,540x337,640x400,720x450,1080x675,1280x800,1440x900,2560x1600\u0026from=bu\u0026cs=2560x0","https://sun9-57.userapi.com/s/v1/ig2/WEwsvxjTjHeexVrH7kXn_v4xL0B_s4m2nFIHnZ58kT1knuK0vPc-MqdCmnYw4NSh2lDx2XUwZeFb3FEr2wVwNlLG.jpg?quality=96\u0026as=32x20,48x30,72x45,108x67,160x100,240x150,360x225,480x300,540x337,640x400,720x450,1080x675,1280x800,1440x900,2560x1600\u0026from=bu\u0026cs=2560x0","https://sun9-54.userapi.com/s/v1/ig2/NKeiZG9zz5EZ_bPuc7KorXj1RaYlxZy7no54_JSH9y1Le_uKYjeYwIy3aXxlhpf6ZxgZo9ME6lfZMtHJ7dCFvA6m.jpg?quality=96\u0026as=32x20,48x30,72x45,108x67,160x100,240x150,360x225,480x300,540x337,640x400,720x450,1080x675,1280x800,1440x900,2560x1600\u0026from=bu\u0026cs=2560x0"]}