{"location":"","locationId":"","title":"","bio":"#ладожское \nоз. Ладожское\n🇷🇺Россия\nПЛОТВА редкий трофей\nПЛОТВА трофеи\nТочка клёва: 69:62, клипса 10 метров\nНаживка: личинка веснянки\nПрикорм: на скрине\nСПОДОМ не подкармливал, ПВА не использовал","pva":"","dip":"","clips":"","bite":"","elements":"","inserts":"","like":"10","fish":"","fishId":"","dateTime":0,"date":"","hash":"","id":0,"reposts":"","points":null,"pointKey":"","groupId":"","images":["https://sun6-21.userapi.com/s/v1/ig2/p6bs2Odw_R12r6s1HMtKyjZ6QNecUedA7RgVIziImC5DcJ1ueWl5-ciUoz4JlGHa5Csm4O4cUs0Zq5FnRkAjlEub.jpg?quality=95\u0026as=32x18,48x27,72x40,108x61,160x90,240x135,360x202,480x270,540x304,640x360,720x405,1080x607,1280x720,1440x810,1920x1080\u0026from=bu\u0026cs=1920x1080","https://sun6-22.userapi.com/s/v1/ig2/oayNNUTNZ9_ItTGmy4LbYKW4m-Yst-aLoRsPGXZAuYb6asUmAuCr9aTfRt2VHg7vLYSrqEX9bmqvb-sI_pLW7nEw.jpg?quality=95\u0026as=32x18,48x27,72x40,108x61,160x90,240x135,360x202,480x270,540x304,640x360,720x405,1080x607,1280x720,1440x810,1920x1080\u0026from=bu\u0026cs=1920x1080","https://sun6-21.userapi.com/s/v1/ig2/zOrZ8NlaV51oBRlfUZAkEMMPteiIunqEEVoyWfNX136Y4J4QIjgRdJsRv7Sg40dr5IF9wvEjR8Z1N7CT9cGODfDc.jpg?quality=95\u0026as=32x18,48x27,72x40,108x61,160x90,240x135,360x202,480x270,540x304,640x360,720x405,1080x607,1280x720,1440x810,1920x1080\u0026from=bu\u0026cs=1920x1080","https://sun6-20.userapi.com/s/v1/ig2/5hwF8KnL9YoAtOhkOb-QxtWVJJrpTDYSO2q8Le5w3mVEd0EjQV6xu9Y-9sZ9aD9lwUJ3FEXOEbmxmymjPo-INowS.jpg?quality=95\u0026as=32x18,48x27,72x40,108x61,160x90,240x135,360x202,480x270,540x304,640x360,720x405,1080x607,1280x720,1440x810,1920x1080\u0026from=bu\u0026cs=1920x1080","https://sun9-1.userapi.com/s/v1/ig2/4_oVyYoJexY8_WSGu_M4aXlXWVD8GMVgIrCkejr6gxocRhN5S3-A-trdQW-4wuoF4pmu-JCMCFwWHrgcOiyOw3C_.jpg?quality=95\u0026as=32x18,48x27,72x40,108x61,160x90,240x135,360x202,480x270,540x304,640x360,720x405,1080x607,1280x720,1440x810,1920x1080\u0026from=bu\u0026cs=1920x1080"]}