{"location":"","locationId":"","title":"","bio":"#архипелаг \nЛадожский Архипелаг \n🇷🇺Россия\nУГОРЬ трофей \nРЯПУШКА трофей \nТочка клева: 380:268, клипса 40 метров\nНаживка: Ёрш \n\nРяпушка клюнула на ту же сборку, наживка: живец корюшки","pva":"","dip":"","clips":"","bite":"","elements":"","inserts":"","like":"4","fish":"","fishId":"","dateTime":0,"date":"","hash":"","id":0,"reposts":"","points":null,"pointKey":"","groupId":"","images":["https://sun6-21.userapi.com/s/v1/ig2/qc2BHiPh0oRyMn4OVx9YuSB0zQoqObtaoBg23tPdDx_nwHmi8UT4aOACdFa6SvfbVr5R3FEhtvJuJe_YCso5NzLy.jpg?quality=95\u0026as=32x18,48x27,72x40,108x61,160x90,240x135,360x202,480x270,540x304,640x360,720x405,1080x607,1280x720\u0026from=bu\u0026cs=1280x720","https://sun9-12.userapi.com/s/v1/ig2/EGTW6Kr5t-Cl1f5J-5KP_qZDv5-WEXKTWrLDmrtBh9hNdeLSn4X1Wo7nsQooMCWuGyoRfjSMPCb-Zkf7jimPyCLL.jpg?quality=95\u0026as=32x15,48x22,72x33,108x50,160x74,240x111,360x166,480x221,540x249,640x295,720x332,1080x498,1280x590,1440x664,2556x1179\u0026from=bu\u0026cs=2556x1179","https://sun9-3.userapi.com/s/v1/ig2/72POc6ARbtC5S7fnckJfGRhdXu37CZ8h7JmTLf3OpuEyT_j98jorN2w8he5v517A-0OyiKDOPvpmFLaDe8ino8Bo.jpg?quality=95\u0026as=32x18,48x27,72x40,108x61,160x90,240x135,360x202,480x270,540x304,640x360,720x405,1080x607,1280x720\u0026from=bu\u0026cs=1280x720","https://sun9-10.userapi.com/s/v1/ig2/Dr5lN5ysC59mItHPlaAT-7bXjVGl3Jp--0YZbmWO5lwdtFhXSK2FKff-3v7Y-9oWwThe_g2GpfUXE8bBbZZgNO4D.jpg?quality=95\u0026as=32x18,48x27,72x40,108x61,160x90,240x135,360x202,480x270,540x304,640x360,720x405,1080x607,1280x720\u0026from=bu\u0026cs=1280x720","https://sun9-78.userapi.com/s/v1/ig2/0ebeb-oS-IM3_Ssv1n0y_2eXC5u6gQY2EtgNXiG9XCys4OJ9PVPD5_lvKmmQbEytPy7MQYHK1FzEelWTOLL10oDk.jpg?quality=95\u0026as=32x18,48x27,72x40,108x61,160x90,240x135,360x202,480x270,540x304,640x360,720x405,1080x607,1280x720\u0026from=bu\u0026cs=1280x720"]}