{"location":"","locationId":"","title":"","bio":"#тунгуска \nр. Нижняя Тунгуска \n🇷🇺Россия \nПЕСКАРЬ СИБИРСКИЙ троф\nТочка клева:152-125 клипса 8 метров\nНаживка и сборка на скрине\nВсем Н.Х.Н.Ч.\n\npp4farmtrof \nVK - pp4farmtrof \nVK - PP4FARMTROF","pva":"","dip":"","clips":"","bite":"","elements":"","inserts":"","like":"4","fish":"","fishId":"","dateTime":0,"date":"","hash":"","id":0,"reposts":"","points":null,"pointKey":"","groupId":"","images":["https://sun9-55.userapi.com/s/v1/if2/oS7aI_vRk5wm14T1PspZWRm2osRoV7tF1ple3uK_vc4hCLAvoM5UYAlGrdspF3uP5IaAnAFoN6BFtmbUYp8_4WIm.jpg?quality=95\u0026as=32x18,48x27,72x40,108x61,160x90,240x135,360x202,480x270,540x304,640x360,720x405,1080x607,1280x720,1440x810,1920x1080\u0026from=bu\u0026cs=1920x1080","https://sun9-54.userapi.com/s/v1/if2/tJ34XYtnnHzkS3PEvohoVJsE3m1QvJHBb-DZGfeRZtrhqxh3dbuQIjNvNoWOw3-ZvkeG8AUt4HKPgFUgLAV4tu4l.jpg?quality=95\u0026as=32x18,48x27,72x40,108x61,160x90,240x135,360x202,480x270,540x304,640x360,720x405,1080x607,1280x720,1440x810,1920x1080\u0026from=bu\u0026cs=1920x1080","https://sun9-70.userapi.com/s/v1/if2/-LVzHqAOwWTh3AYEt4K-jyUXQHuLr4yq75BSpxOU8g9PxA6iejK_2NrVPEDlPywWNZousMCYUA3wgo9378ZiX48h.jpg?quality=95\u0026as=32x18,48x27,72x40,108x61,160x90,240x135,360x202,480x270,540x304,640x360,720x405,1080x607,1280x720,1440x810,1920x1080\u0026from=bu\u0026cs=1920x1080","https://sun9-12.userapi.com/s/v1/if2/v42S3wtJ-dMbWe48tnwwsKWOmZHqiBqkjKo19pB31knWH4JwH1nQg-oqTcqz8v8AwiaHOJF8YmOhe_Zz9LalJeg8.jpg?quality=95\u0026as=32x18,48x27,72x40,108x61,160x90,240x135,360x202,480x270,540x304,640x360,720x405,1080x607,1280x720,1440x810,1920x1080\u0026from=bu\u0026cs=1920x1080","https://sun6-22.userapi.com/s/v1/if2/oQe8YLDbK6gpOTjqymanqIOBdz-1r_W0DVg8NhkGxZMrRdTqmDsiVh-B44qTLGoEs0IGxhatZCpor2VzlFULxEfu.jpg?quality=95\u0026as=32x18,48x27,72x40,108x61,160x90,240x135,360x202,480x270,540x304,640x360,720x405,1080x607,1280x720,1440x810,1920x1080\u0026from=bu\u0026cs=1920x1080"]}