{"location":"","locationId":"","title":"","bio":"#норвежское \nНорвежское море \n🇷🇺Россия \nОКУНЬ МОРСКОЙ НОРВЕЖСКИЙ\nТочка клева: яма 120 метров \nПриманка: Fire Gummi Eel 8/0 05\nДвижение в придонном слое\n\nВся информация по РР4 на нашем сайте - rr4farmtrof.com/","pva":"","dip":"","clips":"","bite":"","elements":"","inserts":"","like":"5","fish":"","fishId":"","dateTime":0,"date":"","hash":"","id":0,"reposts":"","points":null,"pointKey":"","groupId":"","images":["https://sun6-20.userapi.com/s/v1/ig2/idvZ4sScOkqdStUuIcGwTSUPTMw4TO79TfQYGOxk-wsXK0XMAQjN7YEraoos18NaPJYryZtOWcjOmDuYqDb5VZC4.jpg?quality=95\u0026as=32x18,48x27,72x40,108x61,160x90,240x135,360x202,480x270,540x304,640x360,720x405,1080x607,1280x720,1440x810,1920x1080\u0026from=bu\u0026cs=1920x0","https://sun9-75.userapi.com/s/v1/ig2/eu8kAx9Ss4yX9aa44ex6zvO2rn8LWCq3GXrWELjRy3hvWCZh6Z3ytc14RedRF9acZlkWgsQ1Z3U8NpeDqrtMRQcM.jpg?quality=95\u0026as=32x18,48x27,72x40,108x61,160x90,240x135,360x202,480x270,540x304,640x360,720x405,1080x607,1280x720,1440x810,1920x1080\u0026from=bu\u0026cs=1920x0","https://sun9-54.userapi.com/s/v1/ig2/zMHJorWvVK7BZsSc4iBcq_bptQ4fbFMOUcrrbdxm24v1q2RwohvStViRROJOjwvkQ8B0pCrc_F6zKq-pHM9eTSIu.jpg?quality=95\u0026as=32x18,48x27,72x40,108x61,160x90,240x135,360x202,480x270,540x304,640x360,720x405,1080x607,1280x720,1440x810,1920x1080\u0026from=bu\u0026cs=1920x0","https://sun9-80.userapi.com/s/v1/ig2/cmec_aM8270f-goDlU02xS0zY6055cNFs7OIBxFlrRwsMcqyGpd6wxAZR0mi8Wcpdqlr4p0ZE_0ZMYFILVz4D1jg.jpg?quality=95\u0026as=32x18,48x27,72x40,108x61,160x90,240x135,360x202,480x270,540x304,640x360,720x405,1080x607,1280x720,1440x810,1920x1080\u0026from=bu\u0026cs=1920x0","https://sun6-21.userapi.com/s/v1/ig2/IpqiVD2Nb9e1hZ-fuJXlGwA8EglsFUCitKfcuRIA8RMi832CJ8IQRSWJk4H36dFYElnpI0T7302psCbqk6RSYr-e.jpg?quality=95\u0026as=32x18,48x27,72x40,108x61,160x90,240x135,360x202,480x270,540x304,640x360,720x405,1080x607,1280x720,1440x810,1920x1080\u0026from=bu\u0026cs=1920x0","https://sun9-33.userapi.com/s/v1/ig2/uq6zODSD8UDnYe7q_Ow3NLbSynJeuYmCL2-LrWafzl5Db0lbMCH-ST50d6KEj8w4AdjSC-s-gID8VyX-noY3wEQx.jpg?quality=95\u0026as=32x18,48x27,72x40,108x61,160x90,240x135,360x202,480x270,540x304,640x360,720x405,1080x607,1280x720,1440x810,1920x1080\u0026from=bu\u0026cs=1920x0"]}