{"location":"","locationId":"","title":"","bio":"#норвежское \nНорвежское море \n🇷🇺Россия \nОКУНЬ МОРСКОЙ ЗОЛОТИСТЫЙ троф\nЛовил около 3 часов \nКвадрат H3, пилкинг в придонном слое\nNatural Squid - 23 - 03\nТочка не про фарм, но редкие виды пролетают ;)","pva":"","dip":"","clips":"","bite":"","elements":"","inserts":"","like":"10","fish":"","fishId":"","dateTime":0,"date":"","hash":"","id":0,"reposts":"","points":null,"pointKey":"","groupId":"","images":["https://sun6-23.userapi.com/s/v1/ig2/IthSpjb48i5Rj-QzjMMFMSi25SSGtnueJG8n2S998NVxrsPrm8pSruI5qShl_B2UhhKBWeAgHVAU-TPts8UB-1KM.jpg?quality=95\u0026as=32x18,48x27,72x40,108x61,160x90,240x135,360x202,480x270,540x304,640x360,720x405,1080x607,1280x720,1440x810,1920x1080\u0026from=bu\u0026cs=1920x1080","https://sun6-23.userapi.com/s/v1/ig2/BfetC653ZJ6XCT512jsKnAevblb-BHCupKb_Az9VT74XJo6O-YYCw_R8tIgPksQuIZeQy7ZTIbv-X-2_bSlajwDu.jpg?quality=95\u0026as=32x18,48x27,72x40,108x61,160x90,240x135,360x202,480x270,540x304,640x360,720x405,1080x607,1280x720,1440x810,1920x1080\u0026from=bu\u0026cs=1920x1080","https://sun6-22.userapi.com/s/v1/ig2/EMOS5xF2cdgksiXCTsCOj42BBgGySZHrfrHugvha8KX8yW7OAfnDTyu7TcBz21rCJJ-UpHkYxDqb70zZZpU8yCU5.jpg?quality=95\u0026as=32x18,48x27,72x40,108x61,160x90,240x135,360x202,480x270,540x304,640x360,720x405,1080x607,1280x720,1440x810,1920x1080\u0026from=bu\u0026cs=1920x1080","https://sun6-22.userapi.com/s/v1/ig2/Cs25mnr9nBCGrMId7ZlQ7OeXysjbqtahHFTyfCx_riuOiq5povTsaqZNGOZQuMm2G8Ehm767yLp5y5y0l1EuUxUS.jpg?quality=95\u0026as=32x18,48x27,72x40,108x61,160x90,240x135,360x202,480x270,540x304,640x360,720x405,1080x607,1280x720,1440x810,1920x1080\u0026from=bu\u0026cs=1920x1080","https://sun6-23.userapi.com/s/v1/ig2/zK3ysC6K5WtMKeWgnSU792ki9g6_cQPcoDtpGJJ3EZnILZJaY3AUuJ0rv7-_umrg7QK4KAECLpU5dNq15KkYgBs3.jpg?quality=95\u0026as=32x18,48x27,72x40,108x61,160x90,240x135,360x202,480x270,540x304,640x360,720x405,1080x607,1280x720,1440x810,1920x1080\u0026from=bu\u0026cs=1920x1080","https://sun6-21.userapi.com/s/v1/ig2/PApL7pQtUWl8Y9uH7E7aI3H4WtkDuhU6pCczII4wDc6Tm1cUbyvc-qgzIIMNkpBHdcAvbnxh_6QXfMH0RW8Ps3BG.jpg?quality=95\u0026as=32x18,48x27,72x40,108x61,160x90,240x135,360x202,480x270,540x304,640x360,720x405,1080x607,1280x720,1440x810,1920x1080\u0026from=bu\u0026cs=1920x1080"]}