{"location":"","locationId":"","title":"","bio":"#норвежское \nНорвежское море\n🇷🇺Россия\nМАКРЕЛЬ АТЛАНТИЧЕСКАЯ\nТочка клева: яма 41 метр\nПриманка: квикер 4.5-007\nЛегкий пилкинг в придонном слое\n\nВся информация по РР4 на нашем сайте - rr4farmtrof.com/","pva":"","dip":"","clips":"","bite":"","elements":"","inserts":"","like":"9","fish":"","fishId":"","dateTime":0,"date":"","hash":"","id":0,"reposts":"","points":null,"pointKey":"","groupId":"","images":["https://sun9-49.userapi.com/s/v1/ig2/aVkl_ywqqMSB2fhfRMHjyoW0rDoLRiLcM81XuF5yJdDUCUX9BORveM6BLeUVdqvADQmsrDp-AMIX_mDWX5RrQnWH.jpg?quality=95\u0026as=32x18,48x27,72x40,108x61,160x90,240x135,360x202,480x270,540x304,640x360,720x405,1080x607,1280x720,1440x810,1920x1080\u0026from=bu\u0026cs=1920x0","https://sun9-42.userapi.com/s/v1/ig2/9AhUfthv8yAhjDsPfOvNSrj6NYqZ26hrLqvK2RIxiqdnjVzNsoGCETEtlrADDlwauZUMfq_Gr6r0lukJgCpR8JC6.jpg?quality=95\u0026as=32x18,48x27,72x40,108x61,160x90,240x135,360x202,480x270,540x304,640x360,720x405,1080x607,1280x720,1440x810,1920x1080\u0026from=bu\u0026cs=1920x0","https://sun9-43.userapi.com/s/v1/ig2/cWpVK_QzzTfPLcrUtrfnUkJXGsCvbes82r1aGM3mudiyuHMM9pSgeR_C-vEOPevYZ1lWjubEcSU_ea6sQLAq3nZ3.jpg?quality=95\u0026as=32x18,48x27,72x40,108x61,160x90,240x135,360x202,480x270,540x304,640x360,720x405,1080x607,1280x720,1440x810,1920x1080\u0026from=bu\u0026cs=1920x0","https://sun9-50.userapi.com/s/v1/ig2/I-ylKvrDiJnMUgrftDTuvbUEeAP1yCovg-MAA8Y-F6cztj9_VBY9WXNdn95Z6rn6G96l5RTqcxh62SmMwBvPfteI.jpg?quality=95\u0026as=32x18,48x27,72x40,108x61,160x90,240x135,360x202,480x270,540x304,640x360,720x405,1080x607,1280x720,1440x810,1920x1080\u0026from=bu\u0026cs=1920x0","https://sun6-21.userapi.com/s/v1/ig2/d8FAgwBuSZYkqdN92bt91BgKDpzFLgAyev7kz8HEk_z08alfPAjiFvJgIwRBeMRAzn-nM7q5k6la82EOsgcG5r7M.jpg?quality=95\u0026as=32x18,48x27,72x40,108x61,160x90,240x135,360x202,480x270,540x304,640x360,720x405,1080x607,1280x720,1440x810,1920x1080\u0026from=bu\u0026cs=1920x0"]}