{"location":"","locationId":"","title":"","bio":"#норвежское \nНорвежское море \n🇷🇺Россия \nМОЛЬВА ГОЛУБАЯ трофей \n215 яма, легкий пилкинг в придонном слое \nПробую разные ямы и разные приманки. Попалась вот такая мольвочка. На сколько залет, не знаю. Пробуйте","pva":"","dip":"","clips":"","bite":"","elements":"","inserts":"","like":"5","fish":"","fishId":"","dateTime":0,"date":"","hash":"","id":0,"reposts":"","points":null,"pointKey":"","groupId":"","images":["https://sun6-21.userapi.com/s/v1/ig2/S7-r63csVzoWikTm-c9XKLoJKlpNmBJBEObOFFYxsJHMMFN6R5jAZchmGT2lEJV1aYtcX5BFG5gOuc1IvoM6sxcN.jpg?quality=96\u0026as=32x13,48x20,72x30,108x45,160x67,240x100,360x150,480x201,540x226,640x267,720x301,1080x451,1280x535\u0026from=bu\u0026cs=1280x535","https://sun6-22.userapi.com/s/v1/ig2/EWtSbEWWSb89PSinen-1xgzlnU-o1ELAN5sjzybT3Mqk28m2qWYEXLDmcdWv5As3Y_uvyn9TAJDZJtwioDkbZjJv.jpg?quality=96\u0026as=32x13,48x20,72x30,108x45,160x67,240x100,360x150,480x201,540x226,640x267,720x301,1080x451,1280x535\u0026from=bu\u0026cs=1280x535","https://sun6-23.userapi.com/s/v1/ig2/NqwhnP11pol2Q_-BTQZQuqhVG4t_JxsPeCQpQ0aCh6hHPTNuVo5J3X-q4V76R3G622psNqj5YQng81FaxNdEWI96.jpg?quality=96\u0026as=32x13,48x20,72x30,108x45,160x67,240x100,360x150,480x201,540x226,640x267,720x301,1080x451,1280x535\u0026from=bu\u0026cs=1280x535","https://sun6-22.userapi.com/s/v1/ig2/wR-cQSCPTFR4SNWeFq4L99VVG8XlaPHEBSTkzSXw8gWtCQ762xFksi9n9OMp70MRNhYie90STZZrv5gza4OnPvB3.jpg?quality=96\u0026as=32x13,48x20,72x30,108x45,160x67,240x100,360x150,480x201,540x226,640x267,720x301,1080x451,1280x535\u0026from=bu\u0026cs=1280x535","https://sun6-20.userapi.com/s/v1/ig2/YddZe3Eid6H3Ec6qYKU17Trbslpp-DPSKt6dC1rQmp49KP29voRVOqg4r6CNrJtaFKWP7MG1fb8xmblo9xQeH2mq.jpg?quality=96\u0026as=32x31,48x47,72x71,108x106,160x158,240x236,360x354,480x473,540x532,640x630,647x637\u0026from=bu\u0026cs=647x637"]}