{"location":"","locationId":"","title":"","bio":"#норвежское\nНорвежское море\n🇷🇺 Россия\nОКУНЬ МОРСКОЙ ЗОЛОТИСТЫЙ\nТочка клева: яма 133 метра\nПриманка: Stor Fisk M25-600 #17\n\nВся информация по РР4 на нашем сайте - https://rr4farmtrof.com/","pva":"","dip":"","clips":"","bite":"","elements":"","inserts":"","like":"3","fish":"","fishId":"","dateTime":0,"date":"","hash":"","id":0,"reposts":"","points":null,"pointKey":"","groupId":"","images":["https://sun9-59.userapi.com/s/v1/ig2/Ev2tDVLUnupPwmIVkzFkSfq8Ttotbv17Vj7ZMSfieXlYBi6ol6ZKtqepq2KKo4Tph-bx5_y5fIGEmlo9kodP0YPW.jpg?quality=96\u0026as=32x18,48x27,72x40,108x61,160x90,240x135,360x202,480x270,540x304,640x360,720x405,1080x607,1280x720,1440x810,1920x1080\u0026from=bu\u0026cs=1920x0","https://sun9-76.userapi.com/s/v1/ig2/-4H7z-51QifiMC36KX8VatnP-T1Q8fQF7FlFKopkKSql9VC7m6a6Tqp8eDGp8HsqPqcCFHBANsVwn4IO0GdIB3p0.jpg?quality=96\u0026as=32x18,48x27,72x40,108x61,160x90,240x135,360x202,480x270,540x304,640x360,720x405,1080x607,1280x720,1440x810,1920x1080\u0026from=bu\u0026cs=1920x0","https://sun9-27.userapi.com/s/v1/ig2/FGVtxA1XZg9o2_zM557kUtbwX3pyTZz10Dymuc6dOFYp00tNAP3XS7vGLGSB6oahsMPx0jV0JRmku9SUKHDaCPw5.jpg?quality=96\u0026as=32x18,48x27,72x40,108x61,160x90,240x135,360x202,480x270,540x304,640x360,720x405,1080x607,1280x720,1440x810,1920x1080\u0026from=bu\u0026cs=1920x0","https://sun9-60.userapi.com/s/v1/ig2/lOcWJwEU-N2NzOHiyl2wdPgEsAnylQBIt0l70cWWbaA-eojH48g46MwSB32Et4eaFTBtAj_kssNj111a8ORXgogi.jpg?quality=96\u0026as=32x32,48x48,72x72,108x108,160x160,240x240,360x360,480x480,540x540,640x640,644x644\u0026from=bu\u0026cs=644x0"]}