{"location":"","locationId":"","title":"","bio":"#норвежское\nНорвежское море\n🇷🇺 Россия\nТУНЕЦ ГОЛУБОЙ\nТочка клева: яма 75 метров\nКлипса: 20 метров\nПриманка: Natural Squid - 23 - 07\n\nКомментарий игрока:\n\"на падении\"\n\nВся информация по РР4 на нашем сайте - https://rr4farmtrof.com/","pva":"","dip":"","clips":"","bite":"","elements":"","inserts":"","like":"0","fish":"","fishId":"","dateTime":0,"date":"","hash":"","id":0,"reposts":"","points":null,"pointKey":"","groupId":"","images":["https://sun9-53.userapi.com/s/v1/ig2/oza3AyesF72KWM5zDqGsdIEX-658u6NK9rsknrVghE7NnvBn1BLqcS70YwILt5I0F1EdaBgynWx4TtoWjWSkDMGK.jpg?quality=96\u0026as=32x18,48x27,72x40,108x61,160x90,240x135,360x202,480x270,540x304,640x360,720x405,1080x607,1280x720,1440x810,1920x1080\u0026from=bu\u0026cs=1920x0","https://sun9-17.userapi.com/s/v1/ig2/dZrbbDSyvbIBJ9SJj4DaVVmRlK9F4tgoggxq34t1iquPTQuOsLBzBKlmYYLSrJONqCbOT0Xm0lkNkwq1NcVCCaNO.jpg?quality=96\u0026as=32x18,48x27,72x40,108x61,160x90,240x135,360x202,480x270,540x304,640x360,720x405,1080x607,1280x720,1440x810,1920x1080\u0026from=bu\u0026cs=1920x0","https://sun9-49.userapi.com/s/v1/ig2/vzo-qAf1yME7XRqtvopFC_qLbKCzTVZTKVG7v65zlljT886aphgSNRxozQigMg0Uvehg2QDOCh4XALyfTinMFO56.jpg?quality=96\u0026as=32x18,48x27,72x40,108x61,160x90,240x135,360x202,480x270,540x304,640x360,720x405,1080x607,1280x720,1440x810,1920x1080\u0026from=bu\u0026cs=1920x0","https://sun9-42.userapi.com/s/v1/ig2/vU9Dih1KQd62P9m7aiYpL1TYeOV1ZMfEt2Qge_UgRYYnVuqvHwvmomMoiXzB9o8jqGRokKTeRw2liSqREdtz4vDb.jpg?quality=96\u0026as=32x18,48x27,72x40,108x61,160x90,240x135,360x202,480x270,540x304,640x360,720x405,1080x607,1280x720,1440x810,1920x1080\u0026from=bu\u0026cs=1920x0","https://sun9-73.userapi.com/s/v1/ig2/4jLr0AI70uYvZdf0Dmys_r0JjyawRZd8_KFUrsPSWhC0vnt2rzj4myL16yVjOCCAXuOfzjCIiIk17-WPIoBuJ9uT.jpg?quality=96\u0026as=32x32,48x48,72x72,108x107,160x159,240x238,360x358,480x477,540x537,640x636,644x640\u0026from=bu\u0026cs=644x0"]}