{"location":"","locationId":"","title":"","bio":"#острог \nоз. Старый Острог \n🇷🇺Россия\nПЛОТВА ОБЫКНОВЕННАЯ \nЛЕЩ \nТочка клева: 52:32 \nКлипса: 10 метров \nНаживка: каша перловая\nУтро - вечер: плотва \nВечер - утро: лещ \nКрюк большой 1\n \nВся информация по РР4 на нашем сайте - rr4farmtrof.com/","pva":"","dip":"","clips":"","bite":"","elements":"","inserts":"","like":"5","fish":"","fishId":"","dateTime":0,"date":"","hash":"","id":0,"reposts":"","points":null,"pointKey":"","groupId":"","images":["https://sun9-88.userapi.com/s/v1/ig2/cQbCpDbd_L7nKjJe4KWyoMvt2xXgpD9sXCF1OSJCQyOCq1ghqMg76aqYxlD1EW3Is68pC61WmEtcV6tHqL6kGfmh.jpg?quality=95\u0026as=32x18,48x27,72x40,108x61,160x90,240x135,360x202,480x270,540x304,640x360,720x405,1080x607,1280x720,1440x810,1920x1080\u0026from=bu\u0026cs=1920x0","https://sun9-55.userapi.com/s/v1/ig2/-Xy-CX97bhWI-yvmRDbT9jKZxE5cgWR2cER3l6IS47NRzAnhn2l3faA7q6NuIms1xzn4h9N9Pgn-t0FGa0eXs3ZK.jpg?quality=95\u0026as=32x18,48x27,72x40,108x61,160x90,240x135,360x202,480x270,540x304,640x360,720x405,1080x607,1280x720,1440x810,1920x1080\u0026from=bu\u0026cs=1920x0","https://sun9-13.userapi.com/s/v1/ig2/2pLc1czJ0ldh1Q-eA9iDkKx71sT3myhwcIaoeSLWC1SI8N8C9OrmEXYOoE5WxlAgwJ4RrE1nMj1OjP690RsDAiHr.jpg?quality=95\u0026as=32x18,48x27,72x40,108x61,160x90,240x135,360x202,480x270,540x304,640x360,720x405,1080x607,1280x720,1440x810,1920x1080\u0026from=bu\u0026cs=1920x0","https://sun9-79.userapi.com/s/v1/ig2/Pvg_D-HF9lqCSire3tAgsARSov-LwjBGJYOyft0kfihUSxypuOypUxmbp8mJMKVRMGH43OCnuSvodgnaB59VEJ5b.jpg?quality=95\u0026as=32x18,48x27,72x40,108x61,160x90,240x135,360x202,480x270,540x304,640x360,720x405,1080x607,1280x720,1440x810,1920x1080\u0026from=bu\u0026cs=1920x0","https://sun9-81.userapi.com/s/v1/ig2/KkyebwzRRZjp1HwHfaRZ25pnwZhuBPmuqJDogDnGri-rwBOgUqDB11W_PeBO2ebql5R5R25meCoAm6AN_NkUtazF.jpg?quality=95\u0026as=32x18,48x27,72x40,108x61,160x90,240x135,360x202,480x270,540x304,640x360,720x405,1080x607,1280x720,1440x810,1920x1080\u0026from=bu\u0026cs=1920x0"]}