{"location":"","locationId":"","title":"","bio":"#острог \nоз. Старый Острог \n🇨🇳 China\nКАРП ЧЕШУЙЧАТЫЙ троф\nТочка клева: 47:37, клипса 17 метров\nНаживка троф: Клубника Pop-Up 20 + иск. кукуруза Клубника\nНаживка 2: Клубника Pop-Up 25 + Клубника Pop-Up 20\nНаживка 3: Клубника Pop-Up 25 + иск. кукуруза Клубника\nДип: Клубника\nПрикорм: молотая кукуруза + клубника 4, 8, 10 + Клубника Pop-Up 15 (дробл) + клубника и специи\n\nпоиск точек клева в VK - https://vk.com/wall-222013971_79277 \nпоиск точек клева в ТГ - https://t.me/pp4farmtrof/50537 \nпредложить пост в VK - https://vk.com/pp4farmtrof \nпредложить пост в ТГ - https://t.me/pp4farmtrof/102648\nгруппа VK (точки клева) - https://vk.com/pp4farmtrof \nсмотреть точки клева в телеграм - https://t.me/pp4farmtrof \nнаш чат телеграм - https://t.me/+uQHedikeO9Y3NmQy \nбарахолка вк - https://vk.com/baraholkamalcevidze \nбарахолка телеграм - https://t.me/pp4farmtrofMARKET \nстримы и видео рр4 - https://www.youtube.com/@rr4.farm.trof.malcevidze \nдискорд-общение - https://discord.gg/AdJGuGFD7Z","pva":"","dip":"","clips":"","bite":"","elements":"","inserts":"","like":"2","fish":"","fishId":"","dateTime":0,"date":"","hash":"","id":0,"reposts":"","points":null,"pointKey":"","groupId":"","images":["https://sun9-27.userapi.com/s/v1/if2/o-yrDwuusQZH0t1FGvf-L8NGfVAEi5ImKg-kInsOijK3Izmz_tk7XH8mIGSpEe2pQqfWs5VGYNiw-Y5jBRifCKZc.jpg?quality=96\u0026as=32x31,48x46,72x69,108x104,160x154,240x230,360x345,480x461,540x518,640x614,692x664\u0026from=bu\u0026cs=692x0","https://sun9-11.userapi.com/s/v1/if2/54UVGlmUAbfoDoXh3xoDghXutncuCPg9yc-yEPIhu9BBqyc_TFsVa1r1TZZAgfRcKJoidQyfKJ2guA7p59iYy3ci.jpg?quality=96\u0026as=32x18,48x26,72x39,108x59,160x88,240x131,360x197,480x263,540x296,640x350,720x394,1080x591,1200x657\u0026from=bu\u0026cs=1200x0","https://sun6-20.userapi.com/s/v1/if2/YpjbIrnrMiz9TJjuHkbSDB48yon-u2fS72IkEA1Gte865yQWLVZFTVP5-RUe0qzeY5bCWqOJWxyyoP8lrFMPS4Mo.jpg?quality=96\u0026as=32x23,48x34,72x51,108x77,160x114,240x171,360x257,480x342,540x385,640x456,720x513,1080x770,1119x798\u0026from=bu\u0026cs=1119x0","https://sun6-23.userapi.com/s/v1/if2/f2hmJoErW4yoTywoXRsDDRB4NQVIQ_4te_eh08WckIFdO8CNKQO5iSt4N4EAAAYnRM6Oh_Gj2S96HClHchNJcouj.jpg?quality=96\u0026as=32x23,48x35,72x53,108x79,160x118,240x176,360x264,480x353,540x397,640x470,720x529,1077x791\u0026from=bu\u0026cs=1077x0","https://sun9-59.userapi.com/s/v1/if2/8_2Y-l59NMcabDpW-BfiwrucrgfWdWCmZ4QnCA1MaXOyLuW3aot-HnX76ft4SGiMzLgEMHzzlmOtIq2F96RUTORV.jpg?quality=96\u0026as=32x23,48x35,72x52,108x78,160x116,240x173,360x260,480x347,540x390,640x462,720x520,1080x780,1101x795\u0026from=bu\u0026cs=1101x0","https://sun6-23.userapi.com/s/v1/if2/F_rYWMfksdlGM2e4EjRJ00BJGe7gBdJha2qvMs32JFw3QMGg6IYM_sRyk50ipeLIxl85FrngZ1vh6iPna6CF9iNW.jpg?quality=96\u0026as=32x25,48x38,72x57,108x85,160x126,240x189,360x283,480x377,540x424,640x503,720x566,1018x800\u0026from=bu\u0026cs=1018x0","https://sun9-86.userapi.com/s/v1/ig2/qxS0GXfi7SI4s4_YfG4VdAx-YCSe7dNTQEP9Z_ege98w9qyNU8yGAdXedJy5nim4aLWV7HzCxLLY6FI51JwGezaw.jpg?quality=96\u0026as=32x32,48x48,72x72,108x107,160x159,240x238,360x358,480x477,540x537,640x636,644x640\u0026from=bu\u0026cs=644x0"]}