{"location":"","locationId":"","title":"","bio":"#острог\nоз. Старый Острог\n🇨🇳 Китай\nЛЕЩ\nФАРМ\nТочка клева: 27:54\nКлипса: 13 метров\nНаживка: тесто творожное\nПрикормка: молотая перловка + вареное пшено + опарыш + мотыль + горошек + анисовое масло\n\nКомментарий игрока:\n\"Старый Острог, фарм на леща.\"\n\nВся информация по РР4 на нашем сайте - https://rr4farmtrof.com/","pva":"","dip":"","clips":"","bite":"","elements":"","inserts":"","like":"1","fish":"","fishId":"","dateTime":0,"date":"","hash":"","id":0,"reposts":"","points":null,"pointKey":"","groupId":"","images":["https://sun9-88.userapi.com/s/v1/ig2/zS2n2OwBS5th3WJC32KpDfiY1f7WZOW1CU7zU3evS59yySSSMtvxckTDJc3CqvqT96lJvqvTjMJFPa3T6GrD1sWV.jpg?quality=96\u0026as=32x18,48x27,72x41,108x61,160x90,240x135,360x203,480x270,540x304,640x360,720x405,1000x563\u0026from=bu\u0026cs=1000x0","https://sun6-21.userapi.com/s/v1/ig2/QhnTlRJ95yeNz6cj3pB_NG2G5l9lP6vfvrLFnRlfZPKmHu4MpiqvbG6eTarBuapmvI1f_QrOe8gH8rmAx8HNHk8u.jpg?quality=96\u0026as=32x18,48x27,72x41,108x61,160x90,240x135,360x203,480x270,540x304,640x360,720x405,1000x563\u0026from=bu\u0026cs=1000x0","https://sun9-34.userapi.com/s/v1/ig2/hbGkt1ai2N_SStjRLTQ6A_rMG_DAuFgGtSME2gN515XzadWQm_pePtFE3f0eqY3Kufi1Niz_NkHQOY-yfmOONmGA.jpg?quality=96\u0026as=32x18,48x27,72x41,108x61,160x90,240x135,360x203,480x270,540x304,640x360,720x405,1000x563\u0026from=bu\u0026cs=1000x0","https://sun9-34.userapi.com/s/v1/ig2/coxgQsFLclA6RQUPlm-3NRd22R84woBlrzGgVrs3qYUuuWOSl-4q2D4OVbZILpJV_8GB3n4OIaYV6wcx7DqjvjUp.jpg?quality=96\u0026as=32x18,48x27,72x41,108x61,160x90,240x135,360x203,480x270,540x304,640x360,720x405,1000x563\u0026from=bu\u0026cs=1000x0"]}