{"location":"","locationId":"","title":"","bio":"#яма \nр. Яма\nГОЛЕЦ СИБИРСКИЙ-УСАЧ троф\nТочка клева: 172:208, клипса 20 метров \nНаживка: ручейник","pva":"","dip":"","clips":"","bite":"","elements":"","inserts":"","like":"11","fish":"","fishId":"","dateTime":0,"date":"","hash":"","id":0,"reposts":"","points":null,"pointKey":"","groupId":"","images":["https://sun6-21.userapi.com/s/v1/ig2/gpO8fQrb2WPN7XjuD5Yr9jcgzA1Y0BvEYTfCjyWaZmPsC1rJySw1paEPT3HDnKvsIV7NW0k-IBw9JCcRJgSmOzMV.jpg?quality=95\u0026as=32x18,48x27,72x41,108x61,160x90,240x135,360x203,480x270,540x304,640x360,720x405,1000x563\u0026from=bu\u0026cs=1000x563","https://sun6-20.userapi.com/s/v1/ig2/iclF-RLE1m1HGsyASTc0abw7DVE4EhgpyLvDzsJ2BUqxnz8zW55HnaYiOf6KtSgZMeW3RFhEXcVbv4ZKd5ddrydX.jpg?quality=95\u0026as=32x18,48x27,72x41,108x61,160x90,240x135,360x203,480x270,540x304,640x360,720x405,1000x563\u0026from=bu\u0026cs=1000x563","https://sun6-20.userapi.com/s/v1/ig2/djJTnYPSO4MgAmxI_PYwQ9p4Wo7hK5j1DdRH_oT5ItQ22xVibIIojyB5_pTKzd4HayBff3qBqAILB8Ry3iBF602_.jpg?quality=95\u0026as=32x18,48x27,72x41,108x61,160x90,240x135,360x203,480x270,540x304,640x360,720x405,1000x563\u0026from=bu\u0026cs=1000x563","https://sun6-20.userapi.com/s/v1/ig2/_TIwxSEFXd-LT3CgdQYXkkqva4LQ0COcjIljQegGu0cnReTi3kQfgKzennwxH4tfAmXoOnEjVKegOC4TsZQQnyGw.jpg?quality=95\u0026as=32x18,48x27,72x41,108x61,160x90,240x135,360x203,480x270,540x304,640x360,720x405,1000x563\u0026from=bu\u0026cs=1000x563","https://sun6-21.userapi.com/s/v1/ig2/Em7tSAtLAiVx671ikmjxDsdfHdhqCO_tILkyZFv2Y8Y3Eme73KE43sZ0bD7FntpAM0ecifNBu3pMTtw0eWQ9-riU.jpg?quality=95\u0026as=32x32,48x48,72x72,108x108,160x160,240x240,360x361,480x481,540x541,640x641\u0026from=bu\u0026cs=640x641"]}