{"location":"","locationId":"","title":"","bio":"#яма \nр. Яма \n🇨🇳 China \nЧАВЫЧА троф\nТочка клева: 194:198, скорость 15\n\nпоиск точек клева в VK - https://vk.com/wall-222013971_79277 \nпоиск точек клева в ТГ - https://t.me/pp4farmtrof/50537 \nпредложить пост в VK - https://vk.com/pp4farmtrof \nпредложить пост в ТГ - https://t.me/pp4farmtrof/109117\nгруппа VK (точки клева) - https://vk.com/pp4farmtrof \nсмотреть точки клева в телеграм - https://t.me/pp4farmtrof \nнаш чат телеграм - https://t.me/+uQHedikeO9Y3NmQy \nбарахолка вк - https://vk.com/baraholkamalcevidze \nбарахолка телеграм - https://t.me/pp4farmtrofMARKET \nстримы рр4 - https://www.twitch.tv/rr4farmtrofmalcevidze","pva":"","dip":"","clips":"","bite":"","elements":"","inserts":"","like":"5","fish":"","fishId":"","dateTime":0,"date":"","hash":"","id":0,"reposts":"","points":null,"pointKey":"","groupId":"","images":["https://sun9-87.userapi.com/s/v1/if2/NkSwZaoyUk2KNLzaOcvrK7Um0I-UTCoruMHqB6S4qKbnMcd_80XEwF8H9mGqdDtA0guuGo_Pkajz7KAUtwrI4Yie.jpg?quality=96\u0026as=32x18,48x27,72x40,108x60,160x89,240x133,360x199,480x266,540x299,640x354,720x398,1080x598,1200x664\u0026from=bu\u0026cs=1200x0","https://sun9-25.userapi.com/s/v1/if2/EifyVu5Gvveutua7A8LzX2LtBK45Qp9WdZER_i-OPe6uMFvD5IRgwmSTpEW3SfDyWzhT94xDaDOjGbOs62rHHp9x.jpg?quality=96\u0026as=32x9,48x13,72x19,108x29,160x43,240x65,360x97,480x130,540x146,640x173,720x194,1080x292,1200x324\u0026from=bu\u0026cs=1200x0","https://sun9-20.userapi.com/s/v1/if2/zzPRSxlwmvvmKP6GtEPqiPaYls65ujlHmPcPNAuSWa-WwWoIgwW2h1y-maqZFUJ6l_6XE4Fbdcjh9oQzf5l2sddp.jpg?quality=96\u0026as=32x19,48x29,72x43,108x64,160x95,240x143,360x214,480x286,540x322,640x381,720x429,1080x643,1200x715\u0026from=bu\u0026cs=1200x0","https://sun9-48.userapi.com/s/v1/if2/FOK9GL0HdAqd9tbHp5H8MpsGGXefnYIbsmw3B5roESK1yFFQa43y8lhHy89iNdobIwtCuWYfssyCGtunsPhiAP-_.jpg?quality=96\u0026as=32x19,48x28,72x42,108x63,160x93,240x140,360x210,480x280,540x315,640x373,720x419,1080x629,1200x699\u0026from=bu\u0026cs=1200x0"]}