{"location":"","locationId":"","title":"","bio":"#донец\nр. Северский Донец\n🇨🇳 China\nОКУНЬ СОЛНЕЧНЫЙ\nШЕМАЯ ЧЕРНОМОРСКАЯ\nЧЕХОНЬ\nТочка клева: 25:144, глубина 100 см, заброс 60%\nНаживка: личинка короеда + червь сурский навозник\n\nпоиск точек клева в VK - https://vk.com/wall-222013971_79277\nпоиск точек клева в ТГ - https://t.me/pp4farmtrof/50537\nпредложить пост - https://vk.com/pp4farmtrof\nгруппа VK (точки клева) - https://vk.com/pp4farmtrof\nсмотреть точки клева в телеграм - https://t.me/pp4farmtrof\nнаш чат телеграм - https://t.me/+uQHedikeO9Y3NmQy\nбарахолка вк - https://vk.com/baraholkamalcevidze\nбарахолка телеграм - https://t.me/pp4farmtrofMARKET\nстримы и видео рр4 - https://www.youtube.com/@rr4.farm.trof.malcevidze\nдискорд-общение - https://discord.gg/AdJGuGFD7Z","pva":"","dip":"","clips":"","bite":"","elements":"","inserts":"","like":"5","fish":"","fishId":"","dateTime":0,"date":"","hash":"","id":0,"reposts":"","points":null,"pointKey":"","groupId":"","images":["https://sun9-78.userapi.com/s/v1/if2/KhaJaYY4fkPSepJJsaJqWrIstl5yqf3HJshKnkdQUpauPRBJFnZOSv6MnkCQEDWw0tnmt9bLNhEyG7jI3cygK8-7.jpg?quality=96\u0026as=32x18,48x26,72x40,108x59,160x88,240x132,360x198,480x264,540x298,640x353,720x397,1000x551\u0026from=bu\u0026cs=1000x551","https://sun9-21.userapi.com/s/v1/if2/wXOE7shIjYqkq3aNdkXByzs9DH1HJLTxPGcenSTxcLxASBfs2fLVuNGXq5P1kn3rNljG9UDlqbr2f2nnpT3h0_Gc.jpg?quality=96\u0026as=32x17,48x26,72x39,108x59,160x87,240x131,360x196,480x261,540x294,640x348,720x392,1000x544\u0026from=bu\u0026cs=1000x544","https://sun9-58.userapi.com/s/v1/if2/nMe4-NqSCwyXQrE76MHkSNzZtcvQru6c3GfPUK2qgqdbW3Vu6cyJm7pvo-hUmacbTYvJMXlupUrrmLmyVznaoZYK.jpg?quality=96\u0026as=32x23,48x34,72x51,108x77,160x113,240x170,360x255,480x340,540x383,640x454,720x510,1000x709\u0026from=bu\u0026cs=1000x709","https://sun9-71.userapi.com/s/v1/if2/6o8h0s-FsN433DaeEVw4vt9bKTFAIubB86D_H5FkU3NcnQijBZuBzgdgY8TLNCS-WVY48Rp0PJGHg7pUbx3c3v4G.jpg?quality=96\u0026as=32x20,48x30,72x45,108x67,160x99,240x149,360x223,480x298,540x335,640x397,720x446,1000x620\u0026from=bu\u0026cs=1000x620","https://sun9-77.userapi.com/s/v1/ig2/aWBSoPvmKwx3AatzDWVLueK0jl89VeWfAgCdHbXJW0NOd18JexlpbhLH0PbYr-myg5ARzTa19WvmMsOV83wdN-eB.jpg?quality=96\u0026as=32x42,48x62,72x94,108x141,160x208,240x312,255x332\u0026from=bu\u0026cs=255x332"]}