{"location":"","locationId":"","title":"","bio":"#донец\nСеверский Донец\n🇨🇳 Китай\nШЕМАЯ ЧЕРНОМОРСКАЯ\nФАРМ\nТочка клева: 165:132\nГлубина: 100 см\nСила заброса: 50%\nНаживка: личинка короеда\n\nКомментарий игрока:\n\"Я пришел в 4 утра и ловил до 16 вечера. Клев неплохой. Кто уже освоился, может, как я, ловить на три удочки по течению. Новичкам советую: утром — черноморская шемая, вечером — лещ. Для охоты за звездой можно попробовать — у меня была недозвезда на 495 г.\"\n\nВся информация по РР4 на нашем сайте - https://rr4farmtrof.com/","pva":"","dip":"","clips":"","bite":"","elements":"","inserts":"","like":"1","fish":"","fishId":"","dateTime":0,"date":"","hash":"","id":0,"reposts":"","points":null,"pointKey":"","groupId":"","images":["https://sun9-23.userapi.com/s/v1/ig2/ZYvBIG7aO4YamLdoQ6j3AUM4Ua2udUNTw3Nh_0-Nc-J-7TKN1hEoyJ-SR3I05_yxprobVuW3AjckSxP00yarfS_S.jpg?quality=96\u0026as=32x24,48x36,72x54,108x81,160x120,240x180,360x270,480x360,540x404,640x479,720x539,1000x749\u0026from=bu\u0026cs=1000x0","https://sun9-50.userapi.com/s/v1/ig2/Xq_qJjZlZrs1uUL6GJ39kTz-EWDQmndJwvytaC3p-rZe-S_bFM_BlEIB3ChLt5cDgOO1oMcwFWNIsuzLMLxPKBPp.jpg?quality=96\u0026as=32x24,48x36,72x54,108x81,160x120,240x180,360x270,480x360,540x404,640x479,720x539,1000x749\u0026from=bu\u0026cs=1000x0","https://sun9-38.userapi.com/s/v1/ig2/LYg1UySKrXxUOax-mipCISgr0EZQZe0oqVeUdlHCbeRBU6V0nskULu3ai3LltloznnVLvfZV0rT8aCDgA-5KgLsV.jpg?quality=96\u0026as=32x24,48x36,72x54,108x81,160x120,240x180,360x270,480x360,540x404,640x479,720x539,1000x749\u0026from=bu\u0026cs=1000x0","https://sun9-79.userapi.com/s/v1/ig2/tLGCUBgopy4WuD7kjsVhWW7q2SAy__Pkn3JpUWdOVN23NhE2XMb0zkCldwomjOL1HZ7bp6ntg8ReauPf8kNYkap0.jpg?quality=96\u0026as=32x32,48x48,72x72,108x109,160x161,240x242,360x363,480x483,540x544,640x644,720x725,1000x1007\u0026from=bu\u0026cs=1000x0"]}