{"location":"","locationId":"","title":"","bio":"#донец\nр. Северский Донец\n🇨🇳 China\nВЫРЕЗУБ трофеи\nот разных игроков\n\nТочка клева: 116:122, клипса 17-18 метров\nПВА: семена рапса + мидии 3,6,8 + дрейссена + соус из мидий\n\nпоиск точек клева в VK - https://vk.com/wall-222013971_79277 \nпоиск точек клева в ТГ - https://t.me/pp4farmtrof/50537 \nпредложить пост - https://vk.com/pp4farmtrof \nгруппа VK (точки клева) - https://vk.com/pp4farmtrof \nсмотреть точки клева в телеграм - https://t.me/pp4farmtrof \nнаш чат телеграм - https://t.me/+uQHedikeO9Y3NmQy \nбарахолка вк - https://vk.com/baraholkamalcevidze \nбарахолка телеграм - https://t.me/pp4farmtrofMARKET \nстримы и видео рр4 - https://www.youtube.com/@rr4.farm.trof.malcevidze \nдискорд-общение - https://discord.gg/AdJGuGFD7Z","pva":"","dip":"","clips":"","bite":"","elements":"","inserts":"","like":"5","fish":"","fishId":"","dateTime":0,"date":"","hash":"","id":0,"reposts":"","points":null,"pointKey":"","groupId":"","images":["https://sun6-23.userapi.com/s/v1/if2/NdhlyIacIcZ_YwtLTUi1rxmr1WC-tqn7EogSsAG2eq-rFdQP2jpVovfVhb0SXfF_5pwmyIKCG1M8_xttO5IjIOSS.jpg?quality=96\u0026as=32x24,48x36,72x54,108x81,160x120,240x180,360x270,480x360,540x405,640x480,720x540,1000x750\u0026from=bu\u0026cs=1000x750","https://sun6-22.userapi.com/s/v1/if2/HPLqgvIcqs77qIdDGn8zPV-IV8sHVnSkuk3ORf_MmrNuD2dLfWgzXYY1607lE2LHLOcOwnwcgw3GrjathwVnYeNi.jpg?quality=96\u0026as=32x16,48x25,72x37,108x55,160x82,240x123,360x184,480x245,540x276,640x327,720x368,935x478\u0026from=bu\u0026cs=935x478","https://sun6-23.userapi.com/s/v1/if2/ZTudO41-CIMmc_WsjomgB0kniI2A9SzHClBXQ6EnRb65MtftQ4Mpj8Dyt28-tsiqdCQ54p2fz0rBd_4GFrO716eZ.jpg?quality=96\u0026as=32x21,48x31,72x47,108x70,160x104,240x156,360x235,480x313,540x352,640x417,720x469,1000x652\u0026from=bu\u0026cs=1000x652","https://sun6-21.userapi.com/s/v1/if2/l4yCFxc-WoocODyt_fDc122-AmwoBkrtSc_Rn6jHyG_BIBHVvaFCJ3EMx-q4FrAsQsV5hsI7Xdq1YGSTLaM3JxN_.jpg?quality=96\u0026as=32x18,48x27,72x41,108x62,160x92,240x137,360x206,480x275,540x309,640x366,720x412,1000x572\u0026from=bu\u0026cs=1000x572","https://sun6-22.userapi.com/s/v1/if2/RwGC1OkRzzJSAbj14pSuyzd77vdNooovmyUyCs1n6JVwrMFd68DsSYylrLLiAdYaZXeUFTrNTxPXwpV_H_kmTqeA.jpg?quality=96\u0026as=32x20,48x30,72x45,108x67,160x100,240x149,360x224,480x299,540x336,599x373\u0026from=bu\u0026cs=599x373","https://sun6-22.userapi.com/s/v1/if2/spD5G4uw6qkzkgalYbmKjoWdRuAx0gUuryvJno-ERcxycu20eCfRaYshgEQkRaUR7SCRZPNjHTHN6bRRHfWaB_jz.jpg?quality=96\u0026as=32x24,48x37,72x55,108x83,160x122,240x183,360x275,480x367,540x413,640x489,720x550,1000x764\u0026from=bu\u0026cs=1000x764","https://sun9-24.userapi.com/s/v1/ig2/CcJJbfVnmQcKko28QetFP1PJV2pXpesv6z4GcmdtXGvMIJq30KnXO6_kGDmUQ0kPYUzoPVWr9uZKsUgsK_pT5STt.jpg?quality=96\u0026as=32x43,48x65,72x98,108x147,160x217,240x326,360x489,480x652,482x655\u0026from=bu\u0026cs=482x655","https://sun6-21.userapi.com/s/v1/if2/RZixia45Vh19-Xr94_Xl4p9iy7fNr8zwyU57mNzg7tXQI_tlIrbjxu00Dhi4p-pFMhSm2_smZGL7CZh988c8XtI-.jpg?quality=96\u0026as=32x31,48x47,72x71,108x106,160x157,240x235,360x353,480x471,540x529,640x627,720x706,816x800\u0026from=bu\u0026cs=816x800"]}