{"location":"","locationId":"","title":"","bio":"#донец\nр. Северский Донец\n🇷🇺 Россия\nЯЗЬ\nТочка клева: 99:133\nКлипса: 12 метров\n\nКомментарий игрока:\n\"Трофеев в чате много, успевайте. Но я поймал только на второй день.\"\n\nВся информация по РР4 на нашем сайте - https://rr4farmtrof.com/","pva":"","dip":"","clips":"","bite":"","elements":"","inserts":"","like":"3","fish":"","fishId":"","dateTime":0,"date":"","hash":"","id":0,"reposts":"","points":null,"pointKey":"","groupId":"","images":["https://sun9-39.userapi.com/s/v1/ig2/0TT-X1g3criJMiFG3XbvOrnj-pFB0mLgqtIjoL6wstXEOC9ER-n7FiggN7pNYQaBocuLt_xsiOAzaJ1wme02TSaB.jpg?quality=96\u0026as=32x18,48x27,72x40,108x61,160x90,240x135,360x202,480x270,540x304,640x360,720x405,1080x607,1280x720\u0026from=bu\u0026cs=1280x0","https://sun9-77.userapi.com/s/v1/ig2/-ikhlIGmozwm8dsp1kGBEJfk6XhwQcT_mvI9Wmqzw3HSpvOPwZXsMKQBojWqY1fDuZ9Q4kSW_6Q8aftYh0MePu7M.jpg?quality=96\u0026as=32x18,48x27,72x40,108x61,160x90,240x135,360x202,480x270,540x304,640x360,720x405,1080x607,1280x720\u0026from=bu\u0026cs=1280x0","https://sun9-47.userapi.com/s/v1/ig2/hXk6URk_xFSReCwH4poqHa0uYxPSj-v7Go7W5kYFfmATxpWhiE_8Zv1i6IES4qlhn1ucN1M0cyP1XmZohrUqPyb4.jpg?quality=96\u0026as=32x18,48x27,72x40,108x61,160x90,240x135,360x202,480x270,540x304,640x360,720x405,1080x607,1280x720\u0026from=bu\u0026cs=1280x0","https://sun9-54.userapi.com/s/v1/ig2/l_0yoIzqXTMPUW0y5TpQiHFcw8NKji5gw5UWTWny0yLLxrZTnJ0cxDyD1N64ndqHqhi1WBFL3TeNuxcn_n8Bh2qb.jpg?quality=96\u0026as=32x18,48x27,72x40,108x61,160x90,240x135,360x202,480x270,540x304,640x360,720x405,1080x607,1280x720\u0026from=bu\u0026cs=1280x0"]}