{"location":"","locationId":"","title":"","bio":"#янтарное\nоз. Янтарное\n🇨🇳 China\nКАРП ЛИНЕЙНЫЙ РАМЧАТЫЙ редкий троф\nКАРП ЛИНЕЙНЫЙ троф\nТочка клева: 64:94, клипса 35 метров\nНаживка: Черная смородина PopUp 25 + Ежевика PopUp 20\nДип: Черная смородина \nПВА: молотая кукуруза + Черная смородина PopUp 10 (дробл) + черная смородина 5, 8 + северная ежевика 8 + черная смородина\nТемпература нормальная\n\nпоиск точек клева в VK - https://vk.com/wall-222013971_79277 \nпоиск точек клева в ТГ - https://t.me/pp4farmtrof/50537 \nпредложить пост в VK - https://vk.com/pp4farmtrof \nпредложить пост в ТГ - https://t.me/pp4farmtrof/102648\nгруппа VK (точки клева) - https://vk.com/pp4farmtrof \nсмотреть точки клева в телеграм - https://t.me/pp4farmtrof \nнаш чат телеграм - https://t.me/+uQHedikeO9Y3NmQy \nбарахолка вк - https://vk.com/baraholkamalcevidze \nбарахолка телеграм - https://t.me/pp4farmtrofMARKET \nстримы и видео рр4 - https://www.youtube.com/@rr4.farm.trof.malcevidze \nдискорд-общение - https://discord.gg/AdJGuGFD7Z","pva":"","dip":"","clips":"","bite":"","elements":"","inserts":"","like":"6","fish":"","fishId":"","dateTime":0,"date":"","hash":"","id":0,"reposts":"","points":null,"pointKey":"","groupId":"","images":["https://sun9-44.userapi.com/s/v1/if2/zpTmkA_cSD6dcJnajMbqJTDrlYEiOcmjVGeqnpKt2FfpALGmjIF084mnTdmCg0w5gCfYsypv0MkwRrHTAbGd7gZ5.jpg?quality=96\u0026as=32x20,48x30,72x45,108x67,160x100,240x150,360x225,480x300,540x337,640x400,720x450,1000x625\u0026from=bu\u0026cs=1000x0","https://sun9-52.userapi.com/s/v1/if2/vhJG7uk1RBx2ORikYXPk3AOaeXx828jMUOKGaDu87jTDvzr6oNishaVDy-9fheiubTD9oDGeF14x5BdIcjW9txHe.jpg?quality=96\u0026as=32x20,48x30,72x45,108x67,160x100,240x150,360x225,480x300,540x337,640x400,720x450,1000x625\u0026from=bu\u0026cs=1000x0","https://sun9-58.userapi.com/s/v1/if2/hHm8L_DUElc6b3S8fEQsEIli3O9766XSg_Vt1-Dq5sMqkwy2WHgLwh2hyEVY823wtfdop_fhH58u1lTuqws-d5D2.jpg?quality=96\u0026as=32x13,48x20,72x29,108x44,160x65,240x98,360x147,480x196,540x220,640x261,720x294,1000x408\u0026from=bu\u0026cs=1000x0","https://sun9-29.userapi.com/s/v1/ig2/t9BTnw8Q-QDennu54tesErrmjRwfLme-0cUM-hf6K4KJGxiS0zYQu2LQRjyIoLyHKrJe9hHm6oC56Rka2lpQslrE.jpg?quality=96\u0026as=32x35,48x52,72x78,108x117,160x173,240x260,360x390,480x520,540x585,640x693,720x779,800x866\u0026from=bu\u0026cs=800x0","https://sun9-38.userapi.com/s/v1/if2/C2OJlHUztPWkFEgeoPqpaqLDBo5WfR5aWNuzxsjpxRbT2RUn7cSlCjHrLe5NRLyOyikuzCSCiV_HC-fEl32qhANc.jpg?quality=96\u0026as=32x20,48x30,72x45,108x67,160x100,240x150,360x225,480x300,540x337,640x400,720x450,1000x625\u0026from=bu\u0026cs=1000x0"]}